Workbook

Sheet Base Ventas
A1: |
A4: Fecha Venta | B4: Mes | C4: No orden | D4: Concepto | E4: Cliente/Proveedor | F4: Codigo | G4: Descripcion del producto | H4: Cantidad | I4: Categoria | J4: Ciudad | K4: Lugar de entrega | L4: Status Despacho | M4: Transportadora | N4: No guia | O4: Fecha de despacho | P4: Fecha de Entrega | Q4: Status entrega | R4: Tiempo de despacho de orden | S4: Tiempo de entrega de la orden | T4: Cumple NNS | U4: Desvío NNS (Hábil) | V4: Reponsable Incumplimiento | W4: Valor despacho | X4: Diferencia valor real vs Estimado | Y4: Causal de Incumplimiento | Z4: Observaciones
A5: 46024 | B5: enero | C5: 100245 | D5: Venta | E5: German Toro | F5: TECUACO | G5: =IFERROR(VLOOKUP(F5,Productos!$A$2:$D$277,2,0)," ") -> Archivador TECU Caramelo | H5: 1 | I5: =IFERROR(VLOOKUP(F5,Productos!$A$2:$D$277,3,0)," ") -> Archivador | J5: Valle del Cauca | K5: Tuluá | L5: =IF(O5>0,"Despachado","En alistamiento") -> Despachado | M5: Envía | N5: 4000927-954101369750 | O5: 46035 | P5: 46036 | Q5: =IF(P5>0,"Entregado","En transito") -> Entregado | R5: =IF(L5="Despachado",NETWORKDAYS.INTL("05/01/2026",O5,11,Valores!$A$2:$A$19)-1,"PTE") -> 6 | S5: =IF(Q5="Entregado",NETWORKDAYS.INTL("05/01/2026",P5,11,Valores!$A$2:$A$19)-1,"PTE") -> 7 | T5: =IF(Q5="Entregado",IFERROR(IF(I5=VLOOKUP(I5,Valores!$K$1:$K$4,1,0),IF(S5<=VLOOKUP(I5,Valores!$K$1:$L$4,2,0),"Cumple","No cumple")),IF(S5<=VLOOKUP(K5,Valores!E:F,2,0),"Cumple","No cumple"))) -> No cumple | U5: =IFERROR(IF(T5="no cumple",S5-VLOOKUP(I5,Valores!$K$1:$L$4,2,0),0),S5-VLOOKUP(K5,Valores!E:F,2,0)) -> 2 | V5: Producción | W5: 71906 | Y5: Disponibilidad materia prima
A6: 46026 | B6: enero | C6: 100246 | D6: Venta | E6: Lizeth lopez | F6: TECUACO | G6: =IFERROR(VLOOKUP(F6,Productos!$A$2:$D$277,2,0)," ") -> Archivador TECU Caramelo | H6: 1 | I6: =IFERROR(VLOOKUP(F6,Productos!$A$2:$D$277,3,0)," ") -> Archivador | J6: Antioquia | K6: Sabaneta | L6: =IF(O6>0,"Despachado","En alistamiento") -> Despachado | M6: Envía | N6: 400089 -954101369783 | O6: 46035 | P6: 46036 | Q6: =IF(P6>0,"Entregado","En transito") -> Entregado | R6: =IF(L6="Despachado",NETWORKDAYS.INTL("05/01/2026",O6,11,Valores!$A$2:$A$19)-1,"PTE") -> 6 | S6: =IF(Q6="Entregado",NETWORKDAYS.INTL("05/01/2026",P6,11,Valores!$A$2:$A$19)-1,"PTE") -> 7 | T6: =IF(Q6="Entregado",IFERROR(IF(I6=VLOOKUP(I6,Valores!$K$1:$K$4,1,0),IF(S6<=VLOOKUP(I6,Valores!$K$1:$L$4,2,0),"Cumple","No cumple")),IF(S6<=VLOOKUP(K6,Valores!E:F,2,0),"Cumple","No cumple"))) -> No cumple | U6: =IFERROR(IF(T6="no cumple",S6-VLOOKUP(I6,Valores!$K$1:$L$4,2,0),0),S6-VLOOKUP(K6,Valores!E:F,2,0)) -> 2 | V6: Producción | W6: 68327 | Y6: Disponibilidad materia prima
A7: 46026 | B7: enero | C7: 100246 | D7: Venta | E7: Lizeth lopez | F7: TECUAFE | G7: =IFERROR(VLOOKUP(F7,Productos!$A$2:$D$277,2,0)," ") -> Archivador TECU Fresno Europeo | H7: 1 | I7: =IFERROR(VLOOKUP(F7,Productos!$A$2:$D$277,3,0)," ") -> Archivador | J7: Antioquia | K7: Sabaneta | L7: =IF(O7>0,"Despachado","En alistamiento") -> Despachado | M7: Envía | N7: 4000898-954101369742 | O7: 46035 | P7: 46036 | Q7: =IF(P7>0,"Entregado","En transito") -> Entregado | R7: =IF(L7="Despachado",NETWORKDAYS.INTL("05/01/2026",O7,11,Valores!$A$2:$A$19)-1,"PTE") -> 6 | S7: =IF(Q7="Entregado",NETWORKDAYS.INTL("05/01/2026",P7,11,Valores!$A$2:$A$19)-1,"PTE") -> 7 | T7: =IF(Q7="Entregado",IFERROR(IF(I7=VLOOKUP(I7,Valores!$K$1:$K$4,1,0),IF(S7<=VLOOKUP(I7,Valores!$K$1:$L$4,2,0),"Cumple","No cumple")),IF(S7<=VLOOKUP(K7,Valores!E:F,2,0),"Cumple","No cumple"))) -> No cumple | U7: =IFERROR(IF(T7="no cumple",S7-VLOOKUP(I7,Valores!$K$1:$L$4,2,0),0),S7-VLOOKUP(K7,Valores!E:F,2,0)) -> 2 | V7: Producción | W7: 68327 | Y7: Disponibilidad materia prima
A8: 46027 | B8: enero | C8: 100248 | D8: Venta | E8: Andres Naranjo | F8: TECUCT | G8: =IFERROR(VLOOKUP(F8,Productos!$A$2:$D$277,2,0)," ") -> Bandeja de cables | H8: 1 | I8: =IFERROR(VLOOKUP(F8,Productos!$A$2:$D$277,3,0)," ") -> Accesorio | J8: Cundinamarca | K8: Mosquera | L8: =IF(O8>0,"Despachado","En alistamiento") -> Despachado | M8: Coordinadora | N8: 3980164-84151477420 | O8: 46027 | P8: 46028 | Q8: =IF(P8>0,"Entregado","En transito") -> Entregado | R8: =IF(L8="Despachado",NETWORKDAYS.INTL(A8,O8,11,Valores!$A$2:$A$19)-1,"PTE") -> 0 | S8: =IF(Q8="Entregado",NETWORKDAYS.INTL(A8,P8,11,Valores!$A$2:$A$19)-1,"PTE") -> 1 | T8: =IF(Q8="Entregado",IFERROR(IF(I8=VLOOKUP(I8,Valores!$K$1:$K$4,1,0),IF(S8<=VLOOKUP(I8,Valores!$K$1:$L$4,2,0),"Cumple","No cumple")),IF(S8<=VLOOKUP(K8,Valores!E:F,2,0),"Cumple","No cumple"))) -> Cumple | U8: =IFERROR(IF(T8="no cumple",S8-VLOOKUP(I8,Valores!$K$1:$L$4,2,0),0),S8-VLOOKUP(K8,Valores!E:F,2,0)) -> 0 | W8: 26681
A9: 46027 | B9: enero | C9: 100249 | D9: Venta | E9: Adriana Urrea | F9: TECUTFE2C-60 | G9: =IFERROR(VLOOKUP(F9,Productos!$A$2:$D$277,2,0)," ") -> Superficie Escritorio Fresno Europeo 120x60 Clasico Small | H9: 1 | I9: =IFERROR(VLOOKUP(F9,Productos!$A$2:$D$277,3,0)," ") -> Superficie | J9: Antioquia | K9: Medellín | L9: =IF(O9>0,"Despachado","En alistamiento") -> Despachado | M9: Coordinadora | N9: 3987477-84151480114 | O9: 46029 | P9: 46030 | Q9: =IF(P9>0,"Entregado","En transito") -> Entregado | R9: =IF(L9="Despachado",NETWORKDAYS.INTL(A9,O9,11,Valores!$A$2:$A$19)-1,"PTE") -> 2 | S9: =IF(Q9="Entregado",NETWORKDAYS.INTL(A9,P9,11,Valores!$A$2:$A$19)-1,"PTE") -> 3 | T9: =IF(Q9="Entregado",IFERROR(IF(I9=VLOOKUP(I9,Valores!$K$1:$K$4,1,0),IF(S9<=VLOOKUP(I9,Valores!$K$1:$L$4,2,0),"Cumple","No cumple")),IF(S9<=VLOOKUP(K9,Valores!E:F,2,0),"Cumple","No cumple"))) -> Cumple | U9: =IFERROR(IF(T9="no cumple",S9-VLOOKUP(I9,Valores!$K$1:$L$4,2,0),0),S9-VLOOKUP(K9,Valores!E:F,2,0)) -> 0 | W9: 25952
A10: 46027 | B10: enero | C10: 100249 | D10: Venta | E10: Adriana Urrea | F10: TECU2FNG | G10: =IFERROR(VLOOKUP(F10,Productos!$A$2:$D$277,2,0)," ") -> Electric Standing Desk GO Negro | H10: 1 | I10: =IFERROR(VLOOKUP(F10,Productos!$A$2:$D$277,3,0)," ") -> Standing Desk | J10: Antioquia | K10: Medellín | L10: =IF(O10>0,"Despachado","En alistamiento") -> Despachado | M10: Coordinadora | N10: 3987474-84151480113 | O10: 46029 | P10: 46030 | Q10: =IF(P10>0,"Entregado","En transito") -> Entregado | R10: =IF(L10="Despachado",NETWORKDAYS.INTL(A10,O10,11,Valores!$A$2:$A$19)-1,"PTE") -> 2 | S10: =IF(Q10="Entregado",NETWORKDAYS.INTL(A10,P10,11,Valores!$A$2:$A$19)-1,"PTE") -> 3 | T10: =IF(Q10="Entregado",IFERROR(IF(I10=VLOOKUP(I10,Valores!$K$1:$K$4,1,0),IF(S10<=VLOOKUP(I10,Valores!$K$1:$L$4,2,0),"Cumple","No cumple")),IF(S10<=VLOOKUP(K10,Valores!E:F,2,0),"Cumple","No cumple"))) -> Cumple | U10: =IFERROR(IF(T10="no cumple",S10-VLOOKUP(I10,Valores!$K$1:$L$4,2,0),0),S10-VLOOKUP(K10,Valores!E:F,2,0)) -> 0 | W10: 43114
A11: 46027 | B11: enero | C11: 100250 | D11: Venta | E11: Duvan Sarmiento | F11: TECUTCO2C-60 | G11: =IFERROR(VLOOKUP(F11,Productos!$A$2:$D$277,2,0)," ") -> Superficie Escritorio Caramelo 120x60 Clasico Small | H11: 1 | I11: =IFERROR(VLOOKUP(F11,Productos!$A$2:$D$277,3,0)," ") -> Superficie | J11: Bogotá y alrededores | K11: Bogotá | L11: =IF(O11>0,"Despachado","En alistamiento") -> Despachado | M11: Coordinadora | N11: 3987838-84151480227 | O11: 46029 | P11: 46030 | Q11: =IF(P11>0,"Entregado","En transito") -> Entregado | R11: =IF(L11="Despachado",NETWORKDAYS.INTL(A11,O11,11,Valores!$A$2:$A$19)-1,"PTE") -> 2 | S11: =IF(Q11="Entregado",NETWORKDAYS.INTL(A11,P11,11,Valores!$A$2:$A$19)-1,"PTE") -> 3 | T11: =IF(Q11="Entregado",IFERROR(IF(I11=VLOOKUP(I11,Valores!$K$1:$K$4,1,0),IF(S11<=VLOOKUP(I11,Valores!$K$1:$L$4,2,0),"Cumple","No cumple")),IF(S11<=VLOOKUP(K11,Valores!E:F,2,0),"Cumple","No cumple"))) -> Cumple | U11: =IFERROR(IF(T11="no cumple",S11-VLOOKUP(I11,Valores!$K$1:$L$4,2,0),0),S11-VLOOKUP(K11,Valores!E:F,2,0)) -> 0 | W11: 25952
A12: 46027 | B12: enero | C12: 100250 | D12: Venta | E12: Duvan Sarmiento | F12: TECU3FBRO | G12: =IFERROR(VLOOKUP(F12,Productos!$A$2:$D$277,2,0)," ") -> Electric Standing Desk PRO Blanco | H12: 1 | I12: =IFERROR(VLOOKUP(F12,Productos!$A$2:$D$277,3,0)," ") -> Standing Desk | J12: Bogotá y alrededores | K12: Bogotá | L12: =IF(O12>0,"Despachado","En alistamiento") -> Despachado | M12: Coordinadora | N12: 3987834-84151480226 | O12: 46029 | P12: 46030 | Q12: =IF(P12>0,"Entregado","En transito") -> Entregado | R12: =IF(L12="Despachado",NETWORKDAYS.INTL(A12,O12,11,Valores!$A$2:$A$19)-1,"PTE") -> 2 | S12: =IF(Q12="Entregado",NETWORKDAYS.INTL(A12,P12,11,Valores!$A$2:$A$19)-1,"PTE") -> 3 | T12: =IF(Q12="Entregado",IFERROR(IF(I12=VLOOKUP(I12,Valores!$K$1:$K$4,1,0),IF(S12<=VLOOKUP(I12,Valores!$K$1:$L$4,2,0),"Cumple","No cumple")),IF(S12<=VLOOKUP(K12,Valores!E:F,2,0),"Cumple","No cumple"))) -> Cumple | U12: =IFERROR(IF(T12="no cumple",S12-VLOOKUP(I12,Valores!$K$1:$L$4,2,0),0),S12-VLOOKUP(K12,Valores!E:F,2,0)) -> 0 | W12: 43114
A13: 46027 | B13: enero | C13: 100250 | D13: Venta | E13: Duvan Sarmiento | F13: TECURECO-80 | G13: =IFERROR(VLOOKUP(F13,Productos!$A$2:$D$277,2,0)," ") -> Repisa Escritorio Caramelo x 80cm | H13: 1 | I13: =IFERROR(VLOOKUP(F13,Productos!$A$2:$D$277,3,0)," ") -> Repisa | J13: Bogotá y alrededores | K13: Bogotá | L13: =IF(O13>0,"Despachado","En alistamiento") -> Despachado | M13: Coordinadora | N13: 3987838-84151480227 | O13: 46029 | P13: 46030 | Q13: =IF(P13>0,"Entregado","En transito") -> Entregado | R13: =IF(L13="Despachado",NETWORKDAYS.INTL(A13,O13,11,Valores!$A$2:$A$19)-1,"PTE") -> 2 | S13: =IF(Q13="Entregado",NETWORKDAYS.INTL(A13,P13,11,Valores!$A$2:$A$19)-1,"PTE") -> 3 | T13: =IF(Q13="Entregado",IFERROR(IF(I13=VLOOKUP(I13,Valores!$K$1:$K$4,1,0),IF(S13<=VLOOKUP(I13,Valores!$K$1:$L$4,2,0),"Cumple","No cumple")),IF(S13<=VLOOKUP(K13,Valores!E:F,2,0),"Cumple","No cumple"))) -> Cumple | U13: =IFERROR(IF(T13="no cumple",S13-VLOOKUP(I13,Valores!$K$1:$L$4,2,0),0),S13-VLOOKUP(K13,Valores!E:F,2,0)) -> 0 | W13: 0
A14: 46028 | B14: enero | C14: 100251 | D14: Venta | E14: Andrés vasquez | F14: TECUTLC8x5-60 | G14: =IFERROR(VLOOKUP(F14,Productos!$A$2:$D$277,2,0)," ") -> Superficie en L Caramelo 180x150cm x60 | H14: 1 | I14: =IFERROR(VLOOKUP(F14,Productos!$A$2:$D$277,3,0)," ") -> Superficie | J14: Bogotá y alrededores | K14: Bogotá | L14: =IF(O14>0,"Despachado","En alistamiento") -> Despachado | M14: Envía | N14: 3987727-954101366327 | O14: 46029 | P14: 46030 | Q14: =IF(P14>0,"Entregado","En transito") -> Entregado | R14: =IF(L14="Despachado",NETWORKDAYS.INTL(A14,O14,11,Valores!$A$2:$A$19)-1,"PTE") -> 1 | S14: =IF(Q14="Entregado",NETWORKDAYS.INTL(A14,P14,11,Valores!$A$2:$A$19)-1,"PTE") -> 2 | T14: =IF(Q14="Entregado",IFERROR(IF(I14=VLOOKUP(I14,Valores!$K$1:$K$4,1,0),IF(S14<=VLOOKUP(I14,Valores!$K$1:$L$4,2,0),"Cumple","No cumple")),IF(S14<=VLOOKUP(K14,Valores!E:F,2,0),"Cumple","No cumple"))) -> Cumple | U14: =IFERROR(IF(T14="no cumple",S14-VLOOKUP(I14,Valores!$K$1:$L$4,2,0),0),S14-VLOOKUP(K14,Valores!E:F,2,0)) -> 0 | W14: 32487
A15: 46028 | B15: enero | C15: 100251 | D15: Venta | E15: Andrés vasquez | F15: TECULFN2 | G15: =IFERROR(VLOOKUP(F15,Productos!$A$2:$D$277,2,0)," ") -> Electric Standing Desk En L Frame Negro 2.0 | H15: 1 | I15: =IFERROR(VLOOKUP(F15,Productos!$A$2:$D$277,3,0)," ") -> Standing Desk | J15: Bogotá y alrededores | K15: Bogotá | L15: =IF(O15>0,"Despachado","En alistamiento") -> Despachado | M15: Coordinadora | N15: 3987490-84151480120 | O15: 46029 | P15: 46031 | Q15: =IF(P15>0,"Entregado","En transito") -> Entregado | R15: =IF(L15="Despachado",NETWORKDAYS.INTL(A15,O15,11,Valores!$A$2:$A$19)-1,"PTE") -> 1 | S15: =IF(Q15="Entregado",NETWORKDAYS.INTL(A15,P15,11,Valores!$A$2:$A$19)-1,"PTE") -> 3 | T15: =IF(Q15="Entregado",IFERROR(IF(I15=VLOOKUP(I15,Valores!$K$1:$K$4,1,0),IF(S15<=VLOOKUP(I15,Valores!$K$1:$L$4,2,0),"Cumple","No cumple")),IF(S15<=VLOOKUP(K15,Valores!E:F,2,0),"Cumple","No cumple"))) -> Cumple | U15: =IFERROR(IF(T15="no cumple",S15-VLOOKUP(I15,Valores!$K$1:$L$4,2,0),0),S15-VLOOKUP(K15,Valores!E:F,2,0)) -> 0 | W15: 65353
A16: 46028 | B16: enero | C16: 100251 | D16: Venta | E16: Andrés vasquez | G16: Servicio Instalación | H16: 1 | I16: Instalación | J16: Bogotá y alrededores | K16: Bogotá | L16: =IF(O16>0,"Despachado","En alistamiento") -> Despachado | M16: N/A | N16: N/A | O16: N/A | P16: N/A | Q16: =IF(P16>0,"Entregado","En transito") -> Entregado | R16: 0 | S16: 0 | T16: 0 | U16: =IFERROR(IF(T16="no cumple",S16-VLOOKUP(I16,Valores!$K$1:$L$4,2,0),0),S16-VLOOKUP(K16,Valores!E:F,2,0)) -> 0 | W16: 0
A17: 46028 | B17: enero | C17: 100252 | D17: Venta | E17: Luis Felipe Valencia Alvarez | F17: TECU2CURN-65 | G17: =IFERROR(VLOOKUP(F17,Productos!$A$2:$D$277,2,0)," ") -> Cajonero 2.0 Unicolor Roble Negro x65cm | H17: 1 | I17: =IFERROR(VLOOKUP(F17,Productos!$A$2:$D$277,3,0)," ") -> Archivador | J17: Quindío | K17: Armenia | L17: =IF(O17>0,"Despachado","En alistamiento") -> Despachado | M17: Particular | N17: N/A | O17: 46042 | P17: 46042 | Q17: =IF(P17>0,"Entregado","En transito") -> Entregado | R17: =IF(L17="Despachado",NETWORKDAYS.INTL(A17,O17,11,Valores!$A$2:$A$19)-1,"PTE") -> 11 | S17: =IF(Q17="Entregado",NETWORKDAYS.INTL(A17,P17,11,Valores!$A$2:$A$19)-1,"PTE") -> 11 | T17: =IF(Q17="Entregado",IFERROR(IF(I17=VLOOKUP(I17,Valores!$K$1:$K$4,1,0),IF(S17<=VLOOKUP(I17,Valores!$K$1:$L$4,2,0),"Cumple","No cumple")),IF(S17<=VLOOKUP(K17,Valores!E:F,2,0),"Cumple","No cumple"))) -> No cumple | U17: =IFERROR(IF(T17="no cumple",S17-VLOOKUP(I17,Valores!$K$1:$L$4,2,0),0),S17-VLOOKUP(K17,Valores!E:F,2,0)) -> 6 | V17: Producción | W17: 50000 | Y17: Disponibilidad materia prima
A18: 46029 | B18: enero | C18: 100256 | D18: Venta | E18: Luis Fernando Cruz Bermudez | F18: TECUTCO7C | G18: =IFERROR(VLOOKUP(F18,Productos!$A$2:$D$277,2,0)," ") -> Superficie Caramelo 170x70 Clasico | H18: 1 | I18: =IFERROR(VLOOKUP(F18,Productos!$A$2:$D$277,3,0)," ") -> Superficie | J18: Bogotá y alrededores | K18: Bogotá | L18: =IF(O18>0,"Despachado","En alistamiento") -> Despachado | M18: Envía | N18: 3990060-954101366844 | O18: 46030 | P18: 46031 | Q18: =IF(P18>0,"Entregado","En transito") -> Entregado | R18: =IF(L18="Despachado",NETWORKDAYS.INTL(A18,O18,11,Valores!$A$2:$A$19)-1,"PTE") -> 1 | S18: =IF(Q18="Entregado",NETWORKDAYS.INTL(A18,P18,11,Valores!$A$2:$A$19)-1,"PTE") -> 2 | T18: =IF(Q18="Entregado",IFERROR(IF(I18=VLOOKUP(I18,Valores!$K$1:$K$4,1,0),IF(S18<=VLOOKUP(I18,Valores!$K$1:$L$4,2,0),"Cumple","No cumple")),IF(S18<=VLOOKUP(K18,Valores!E:F,2,0),"Cumple","No cumple"))) -> Cumple | U18: =IFERROR(IF(T18="no cumple",S18-VLOOKUP(I18,Valores!$K$1:$L$4,2,0),0),S18-VLOOKUP(K18,Valores!E:F,2,0)) -> 0 | W18: 34253
A19: 46029 | B19: enero | C19: 100256 | D19: Venta | E19: Luis Fernando Cruz Bermudez | F19: TECU3FNPRO | G19: =IFERROR(VLOOKUP(F19,Productos!$A$2:$D$277,2,0)," ") -> Electric Standing Desk PRO Negro | H19: 1 | I19: =IFERROR(VLOOKUP(F19,Productos!$A$2:$D$277,3,0)," ") -> Standing Desk | J19: Bogotá y alrededores | K19: Bogotá | L19: =IF(O19>0,"Despachado","En alistamiento") -> Despachado | M19: Coordinadora | N19: 3989846-84151480984 | O19: 46030 | P19: 46032 | Q19: =IF(P19>0,"Entregado","En transito") -> Entregado | R19: =IF(L19="Despachado",NETWORKDAYS.INTL(A19,O19,11,Valores!$A$2:$A$19)-1,"PTE") -> 1 | S19: =IF(Q19="Entregado",NETWORKDAYS.INTL(A19,P19,11,Valores!$A$2:$A$19)-1,"PTE") -> 3 | T19: =IF(Q19="Entregado",IFERROR(IF(I19=VLOOKUP(I19,Valores!$K$1:$K$4,1,0),IF(S19<=VLOOKUP(I19,Valores!$K$1:$L$4,2,0),"Cumple","No cumple")),IF(S19<=VLOOKUP(K19,Valores!E:F,2,0),"Cumple","No cumple"))) -> Cumple | U19: =IFERROR(IF(T19="no cumple",S19-VLOOKUP(I19,Valores!$K$1:$L$4,2,0),0),S19-VLOOKUP(K19,Valores!E:F,2,0)) -> 0 | W19: 44550
A20: 46029 | B20: enero | C20: 100256 | D20: Venta | E20: Luis Fernando Cruz Bermudez | G20: Servicio Instalación | H20: 1 | I20: Instalación | J20: Bogotá y alrededores | K20: Bogotá | L20: =IF(O20>0,"Despachado","En alistamiento") -> Despachado | M20: N/A | N20: N/A | O20: N/A | P20: N/A | Q20: =IF(P20>0,"Entregado","En transito") -> Entregado | R20: 0 | S20: 0 | T20: 0 | U20: =IFERROR(IF(T20="no cumple",S20-VLOOKUP(I20,Valores!$K$1:$L$4,2,0),0),S20-VLOOKUP(K20,Valores!E:F,2,0)) -> 0 | W20: 0
A21: 46029 | B21: enero | C21: 100258 | D21: Venta | E21: Moba Code SAS | F21: TECUTLFE5X70 | G21: =IFERROR(VLOOKUP(F21,Productos!$A$2:$D$277,2,0)," ") -> Superficie Escritorio Fresno Europeo en L 150x70 | H21: 1 | I21: =IFERROR(VLOOKUP(F21,Productos!$A$2:$D$277,3,0)," ") -> Superficie | J21: Tolima | K21: Ibagué | L21: =IF(O21>0,"Despachado","En alistamiento") -> Despachado | M21: Envía | N21: 3990171-954101366854 | O21: 46030 | P21: 46031 | Q21: =IF(P21>0,"Entregado","En transito") -> Entregado | R21: =IF(L21="Despachado",NETWORKDAYS.INTL(A21,O21,11,Valores!$A$2:$A$19)-1,"PTE") -> 1 | S21: =IF(Q21="Entregado",NETWORKDAYS.INTL(A21,P21,11,Valores!$A$2:$A$19)-1,"PTE") -> 2 | T21: =IF(Q21="Entregado",IFERROR(IF(I21=VLOOKUP(I21,Valores!$K$1:$K$4,1,0),IF(S21<=VLOOKUP(I21,Valores!$K$1:$L$4,2,0),"Cumple","No cumple")),IF(S21<=VLOOKUP(K21,Valores!E:F,2,0),"Cumple","No cumple"))) -> Cumple | U21: =IFERROR(IF(T21="no cumple",S21-VLOOKUP(I21,Valores!$K$1:$L$4,2,0),0),S21-VLOOKUP(K21,Valores!E:F,2,0)) -> 0 | W21: 40366
A22: 46029 | B22: enero | C22: 100258 | D22: Venta | E22: Moba Code SAS | F22: TECULFN2 | G22: =IFERROR(VLOOKUP(F22,Productos!$A$2:$D$277,2,0)," ") -> Electric Standing Desk En L Frame Negro 2.0 | H22: 1 | I22: =IFERROR(VLOOKUP(F22,Productos!$A$2:$D$277,3,0)," ") -> Standing Desk | J22: Tolima | K22: Ibagué | L22: =IF(O22>0,"Despachado","En alistamiento") -> Despachado | M22: Coordinadora | N22: 3989863-84151480993 | O22: 46030 | P22: 46031 | Q22: =IF(P22>0,"Entregado","En transito") -> Entregado | R22: =IF(L22="Despachado",NETWORKDAYS.INTL(A22,O22,11,Valores!$A$2:$A$19)-1,"PTE") -> 1 | S22: =IF(Q22="Entregado",NETWORKDAYS.INTL(A22,P22,11,Valores!$A$2:$A$19)-1,"PTE") -> 2 | T22: =IF(Q22="Entregado",IFERROR(IF(I22=VLOOKUP(I22,Valores!$K$1:$K$4,1,0),IF(S22<=VLOOKUP(I22,Valores!$K$1:$L$4,2,0),"Cumple","No cumple")),IF(S22<=VLOOKUP(K22,Valores!E:F,2,0),"Cumple","No cumple"))) -> Cumple | U22: =IFERROR(IF(T22="no cumple",S22-VLOOKUP(I22,Valores!$K$1:$L$4,2,0),0),S22-VLOOKUP(K22,Valores!E:F,2,0)) -> 0 | W22: 65353
A23: 46029 | B23: enero | C23: 100258 | D23: Venta | E23: Moba Code SAS | F23: TECUREFE -47 | G23: =IFERROR(VLOOKUP(F23,Productos!$A$2:$D$277,2,0)," ") -> Repisa Escritorio Fresno Europeo x 47cm | H23: 2 | I23: =IFERROR(VLOOKUP(F23,Productos!$A$2:$D$277,3,0)," ") -> Repisa | J23: Tolima | K23: Ibagué | L23: =IF(O23>0,"Despachado","En alistamiento") -> Despachado | M23: Coordinadora | N23: 3990171-954101366854 | O23: 46030 | P23: 46031 | Q23: =IF(P23>0,"Entregado","En transito") -> Entregado | R23: =IF(L23="Despachado",NETWORKDAYS.INTL(A23,O23,11,Valores!$A$2:$A$19)-1,"PTE") -> 1 | S23: =IF(Q23="Entregado",NETWORKDAYS.INTL(A23,P23,11,Valores!$A$2:$A$19)-1,"PTE") -> 2 | T23: =IF(Q23="Entregado",IFERROR(IF(I23=VLOOKUP(I23,Valores!$K$1:$K$4,1,0),IF(S23<=VLOOKUP(I23,Valores!$K$1:$L$4,2,0),"Cumple","No cumple")),IF(S23<=VLOOKUP(K23,Valores!E:F,2,0),"Cumple","No cumple"))) -> Cumple | U23: =IFERROR(IF(T23="no cumple",S23-VLOOKUP(I23,Valores!$K$1:$L$4,2,0),0),S23-VLOOKUP(K23,Valores!E:F,2,0)) -> 0 | W23: 0
A24: 46029 | B24: enero | C24: 100258 | D24: Venta | E24: Moba Code SAS | F24: TECUBLS | G24: =IFERROR(VLOOKUP(F24,Productos!$A$2:$D$277,2,0)," ") -> Laptop Stand B | H24: 2 | I24: =IFERROR(VLOOKUP(F24,Productos!$A$2:$D$277,3,0)," ") -> Accesorio | J24: Tolima | K24: Ibagué | L24: =IF(O24>0,"Despachado","En alistamiento") -> Despachado | M24: Coordinadora | N24: 3989874-84151480998 | O24: 46030 | P24: 46031 | Q24: =IF(P24>0,"Entregado","En transito") -> Entregado | R24: =IF(L24="Despachado",NETWORKDAYS.INTL(A24,O24,11,Valores!$A$2:$A$19)-1,"PTE") -> 1 | S24: =IF(Q24="Entregado",NETWORKDAYS.INTL(A24,P24,11,Valores!$A$2:$A$19)-1,"PTE") -> 2 | T24: =IF(Q24="Entregado",IFERROR(IF(I24=VLOOKUP(I24,Valores!$K$1:$K$4,1,0),IF(S24<=VLOOKUP(I24,Valores!$K$1:$L$4,2,0),"Cumple","No cumple")),IF(S24<=VLOOKUP(K24,Valores!E:F,2,0),"Cumple","No cumple"))) -> Cumple | U24: =IFERROR(IF(T24="no cumple",S24-VLOOKUP(I24,Valores!$K$1:$L$4,2,0),0),S24-VLOOKUP(K24,Valores!E:F,2,0)) -> 0 | W24: 0
A25: 46029 | B25: enero | C25: 100258 | D25: Venta | E25: Moba Code SAS | F25: TECUBDPA | G25: =IFERROR(VLOOKUP(F25,Productos!$A$2:$D$277,2,0)," ") -> Desk Pad B Negro Azul | H25: 2 | I25: =IFERROR(VLOOKUP(F25,Productos!$A$2:$D$277,3,0)," ") -> Accesorio | J25: Tolima | K25: Ibagué | L25: =IF(O25>0,"Despachado","En alistamiento") -> Despachado | M25: Coordinadora | N25: 3989874-84151480998 | O25: 46030 | P25: 46031 | Q25: =IF(P25>0,"Entregado","En transito") -> Entregado | R25: =IF(L25="Despachado",NETWORKDAYS.INTL(A25,O25,11,Valores!$A$2:$A$19)-1,"PTE") -> 1 | S25: =IF(Q25="Entregado",NETWORKDAYS.INTL(A25,P25,11,Valores!$A$2:$A$19)-1,"PTE") -> 2 | T25: =IF(Q25="Entregado",IFERROR(IF(I25=VLOOKUP(I25,Valores!$K$1:$K$4,1,0),IF(S25<=VLOOKUP(I25,Valores!$K$1:$L$4,2,0),"Cumple","No cumple")),IF(S25<=VLOOKUP(K25,Valores!E:F,2,0),"Cumple","No cumple"))) -> Cumple | U25: =IFERROR(IF(T25="no cumple",S25-VLOOKUP(I25,Valores!$K$1:$L$4,2,0),0),S25-VLOOKUP(K25,Valores!E:F,2,0)) -> 0 | W25: 17787
A26: 46029 | B26: enero | C26: 100258 | D26: Venta | E26: Moba Code SAS | F26: TECUCT | G26: =IFERROR(VLOOKUP(F26,Productos!$A$2:$D$277,2,0)," ") -> Bandeja de cables | H26: 1 | I26: =IFERROR(VLOOKUP(F26,Productos!$A$2:$D$277,3,0)," ") -> Accesorio | J26: Tolima | K26: Ibagué | L26: =IF(O26>0,"Despachado","En alistamiento") -> Despachado | M26: Coordinadora | N26: 3989884-84151481002 | O26: 46030 | P26: 46031 | Q26: =IF(P26>0,"Entregado","En transito") -> Entregado | R26: =IF(L26="Despachado",NETWORKDAYS.INTL(A26,O26,11,Valores!$A$2:$A$19)-1,"PTE") -> 1 | S26: =IF(Q26="Entregado",NETWORKDAYS.INTL(A26,P26,11,Valores!$A$2:$A$19)-1,"PTE") -> 2 | T26: =IF(Q26="Entregado",IFERROR(IF(I26=VLOOKUP(I26,Valores!$K$1:$K$4,1,0),IF(S26<=VLOOKUP(I26,Valores!$K$1:$L$4,2,0),"Cumple","No cumple")),IF(S26<=VLOOKUP(K26,Valores!E:F,2,0),"Cumple","No cumple"))) -> Cumple | U26: =IFERROR(IF(T26="no cumple",S26-VLOOKUP(I26,Valores!$K$1:$L$4,2,0),0),S26-VLOOKUP(K26,Valores!E:F,2,0)) -> 0 | W26: 26681
A27: 46029 | B27: enero | C27: 100258 | D27: Venta | E27: Moba Code SAS | F27: TECUDSG | G27: =IFERROR(VLOOKUP(F27,Productos!$A$2:$D$277,2,0)," ") -> Desk Stool Gris Silla ajustable | H27: 1 | I27: =IFERROR(VLOOKUP(F27,Productos!$A$2:$D$277,3,0)," ") -> Silla | J27: Tolima | K27: Ibagué | L27: =IF(O27>0,"Despachado","En alistamiento") -> Despachado | M27: Coordinadora | N27: 3989900-84151481009 | O27: 46030 | P27: 46031 | Q27: =IF(P27>0,"Entregado","En transito") -> Entregado | R27: =IF(L27="Despachado",NETWORKDAYS.INTL(A27,O27,11,Valores!$A$2:$A$19)-1,"PTE") -> 1 | S27: =IF(Q27="Entregado",NETWORKDAYS.INTL(A27,P27,11,Valores!$A$2:$A$19)-1,"PTE") -> 2 | T27: =IF(Q27="Entregado",IFERROR(IF(I27=VLOOKUP(I27,Valores!$K$1:$K$4,1,0),IF(S27<=VLOOKUP(I27,Valores!$K$1:$L$4,2,0),"Cumple","No cumple")),IF(S27<=VLOOKUP(K27,Valores!E:F,2,0),"Cumple","No cumple"))) -> Cumple | U27: =IFERROR(IF(T27="no cumple",S27-VLOOKUP(I27,Valores!$K$1:$L$4,2,0),0),S27-VLOOKUP(K27,Valores!E:F,2,0)) -> 0 | W27: 27803
A28: 46030 | B28: enero | C28: 100260 | D28: Venta | E28: Jessner Mejía | F28: TECUTFE2C-60 | G28: =IFERROR(VLOOKUP(F28,Productos!$A$2:$D$277,2,0)," ") -> Superficie Escritorio Fresno Europeo 120x60 Clasico Small | H28: 1 | I28: =IFERROR(VLOOKUP(F28,Productos!$A$2:$D$277,3,0)," ") -> Superficie | J28: Cauca | K28: Popayán | L28: =IF(O28>0,"Despachado","En alistamiento") -> Despachado | M28: Coordinadora | N28: 3989921-84151481020 | O28: 46030 | P28: 46032 | Q28: =IF(P28>0,"Entregado","En transito") -> Entregado | R28: =IF(L28="Despachado",NETWORKDAYS.INTL(A28,O28,11,Valores!$A$2:$A$19)-1,"PTE") -> 0 | S28: =IF(Q28="Entregado",NETWORKDAYS.INTL(A28,P28,11,Valores!$A$2:$A$19)-1,"PTE") -> 2 | T28: =IF(Q28="Entregado",IFERROR(IF(I28=VLOOKUP(I28,Valores!$K$1:$K$4,1,0),IF(S28<=VLOOKUP(I28,Valores!$K$1:$L$4,2,0),"Cumple","No cumple")),IF(S28<=VLOOKUP(K28,Valores!E:F,2,0),"Cumple","No cumple"))) -> Cumple | U28: =IFERROR(IF(T28="no cumple",S28-VLOOKUP(I28,Valores!$K$1:$L$4,2,0),0),S28-VLOOKUP(K28,Valores!E:F,2,0)) -> 0 | W28: 29698
A29: 46030 | B29: enero | C29: 100260 | D29: Venta | E29: Jessner Mejía | F29: TECU3FBRO | G29: =IFERROR(VLOOKUP(F29,Productos!$A$2:$D$277,2,0)," ") -> Electric Standing Desk PRO Blanco | H29: 1 | I29: =IFERROR(VLOOKUP(F29,Productos!$A$2:$D$277,3,0)," ") -> Standing Desk | J29: Cauca | K29: Popayán | L29: =IF(O29>0,"Despachado","En alistamiento") -> Despachado | M29: Coordinadora | N29: 3989918-84151481019 | O29: 46030 | P29: 46032 | Q29: =IF(P29>0,"Entregado","En transito") -> Entregado | R29: =IF(L29="Despachado",NETWORKDAYS.INTL(A29,O29,11,Valores!$A$2:$A$19)-1,"PTE") -> 0 | S29: =IF(Q29="Entregado",NETWORKDAYS.INTL(A29,P29,11,Valores!$A$2:$A$19)-1,"PTE") -> 2 | T29: =IF(Q29="Entregado",IFERROR(IF(I29=VLOOKUP(I29,Valores!$K$1:$K$4,1,0),IF(S29<=VLOOKUP(I29,Valores!$K$1:$L$4,2,0),"Cumple","No cumple")),IF(S29<=VLOOKUP(K29,Valores!E:F,2,0),"Cumple","No cumple"))) -> Cumple | U29: =IFERROR(IF(T29="no cumple",S29-VLOOKUP(I29,Valores!$K$1:$L$4,2,0),0),S29-VLOOKUP(K29,Valores!E:F,2,0)) -> 0 | W29: 47674
A30: 46037 | B30: enero | C30: 100260 | D30: Novedad | E30: Jessner Mejía | F30: TECUTFE2C-60 | G30: =IFERROR(VLOOKUP(F30,Productos!$A$2:$D$277,2,0)," ") -> Superficie Escritorio Fresno Europeo 120x60 Clasico Small | H30: 1 | I30: =IFERROR(VLOOKUP(F30,Productos!$A$2:$D$277,3,0)," ") -> Superficie | J30: Cauca | K30: Popayán | L30: =IF(O30>0,"Despachado","En alistamiento") -> Despachado | M30: Coordinadora | N30: 4010063-84151488641 | O30: 46038 | P30: 46039 | Q30: =IF(P30>0,"Entregado","En transito") -> Entregado | R30: =IF(L30="Despachado",NETWORKDAYS.INTL(A30,O30,11,Valores!$A$2:$A$19)-1,"PTE") -> 1 | S30: =IF(Q30="Entregado",NETWORKDAYS.INTL(A30,P30,11,Valores!$A$2:$A$19)-1,"PTE") -> 2 | T30: =IF(Q30="Entregado",IFERROR(IF(I30=VLOOKUP(I30,Valores!$K$1:$K$4,1,0),IF(S30<=VLOOKUP(I30,Valores!$K$1:$L$4,2,0),"Cumple","No cumple")),IF(S30<=VLOOKUP(K30,Valores!E:F,2,0),"Cumple","No cumple"))) -> Cumple | U30: =IFERROR(IF(T30="no cumple",S30-VLOOKUP(I30,Valores!$K$1:$L$4,2,0),0),S30-VLOOKUP(K30,Valores!E:F,2,0)) -> 0 | V30: Producción | W30: 33316 | Z30: Se realizó envío nueva superficie, porque se hicieron las tuercas de inserto en espacios diferente y no se podía atornillar la bandeja.
A31: 46030 | B31: enero | C31: 100261 | D31: Venta | E31: Nicolas Simmonds | F31: TECU2CBC-73 | G31: =IFERROR(VLOOKUP(F31,Productos!$A$2:$D$277,2,0)," ") -> Cajonero 2.0 Bicolor Caramelo x73cm | H31: 1 | I31: =IFERROR(VLOOKUP(F31,Productos!$A$2:$D$277,3,0)," ") -> Archivador | J31: Bogotá y alrededores | K31: Bogotá | L31: =IF(O31>0,"Despachado","En alistamiento") -> Despachado | M31: Envía | N31: 4026700-954101377299 | O31: 46044 | P31: 46045 | Q31: =IF(P31>0,"Entregado","En transito") -> Entregado | R31: =IF(L31="Despachado",NETWORKDAYS.INTL(A31,O31,11,Valores!$A$2:$A$19)-1,"PTE") -> 11 | S31: =IF(Q31="Entregado",NETWORKDAYS.INTL(A31,P31,11,Valores!$A$2:$A$19)-1,"PTE") -> 12 | T31: =IF(Q31="Entregado",IFERROR(IF(I31=VLOOKUP(I31,Valores!$K$1:$K$4,1,0),IF(S31<=VLOOKUP(I31,Valores!$K$1:$L$4,2,0),"Cumple","No cumple")),IF(S31<=VLOOKUP(K31,Valores!E:F,2,0),"Cumple","No cumple"))) -> No cumple | U31: =IFERROR(IF(T31="no cumple",S31-VLOOKUP(I31,Valores!$K$1:$L$4,2,0),0),S31-VLOOKUP(K31,Valores!E:F,2,0)) -> 7 | V31: Producción | W31: 57135 | Y31: Disponibilidad materia prima
A32: 46034 | B32: enero | C32: 100264 | D32: Venta | E32: Alison Ruiz | F32: TECUTB2C-60 | G32: =IFERROR(VLOOKUP(F32,Productos!$A$2:$D$277,2,0)," ") -> Superficie Escritorio Blanco (Niebla) 120x60 Clasico Small | H32: 1 | I32: =IFERROR(VLOOKUP(F32,Productos!$A$2:$D$277,3,0)," ") -> Superficie | J32: Bogotá y alrededores | K32: Bogotá | L32: =IF(O32>0,"Despachado","En alistamiento") -> Despachado | M32: Coordinadora | N32: 4003463-84151486019 | O32: 46037 | P32: 46038 | Q32: =IF(P32>0,"Entregado","En transito") -> Entregado | R32: =IF(L32="Despachado",NETWORKDAYS.INTL(A32,O32,11,Valores!$A$2:$A$19)-1,"PTE") -> 2 | S32: =IF(Q32="Entregado",NETWORKDAYS.INTL(A32,P32,11,Valores!$A$2:$A$19)-1,"PTE") -> 3 | T32: =IF(Q32="Entregado",IFERROR(IF(I32=VLOOKUP(I32,Valores!$K$1:$K$4,1,0),IF(S32<=VLOOKUP(I32,Valores!$K$1:$L$4,2,0),"Cumple","No cumple")),IF(S32<=VLOOKUP(K32,Valores!E:F,2,0),"Cumple","No cumple"))) -> Cumple | U32: =IFERROR(IF(T32="no cumple",S32-VLOOKUP(I32,Valores!$K$1:$L$4,2,0),0),S32-VLOOKUP(K32,Valores!E:F,2,0)) -> 0 | W32: 25952
A33: 46034 | B33: enero | C33: 100264 | D33: Venta | E33: Alison Ruiz | F33: TECU2FNG | G33: =IFERROR(VLOOKUP(F33,Productos!$A$2:$D$277,2,0)," ") -> Electric Standing Desk GO Negro | H33: 1 | I33: =IFERROR(VLOOKUP(F33,Productos!$A$2:$D$277,3,0)," ") -> Standing Desk | J33: Bogotá y alrededores | K33: Bogotá | L33: =IF(O33>0,"Despachado","En alistamiento") -> Despachado | M33: Coordinadora | N33: 4003461-84151486011 | O33: 46037 | P33: 46038 | Q33: =IF(P33>0,"Entregado","En transito") -> Entregado | R33: =IF(L33="Despachado",NETWORKDAYS.INTL(A33,O33,11,Valores!$A$2:$A$19)-1,"PTE") -> 2 | S33: =IF(Q33="Entregado",NETWORKDAYS.INTL(A33,P33,11,Valores!$A$2:$A$19)-1,"PTE") -> 3 | T33: =IF(Q33="Entregado",IFERROR(IF(I33=VLOOKUP(I33,Valores!$K$1:$K$4,1,0),IF(S33<=VLOOKUP(I33,Valores!$K$1:$L$4,2,0),"Cumple","No cumple")),IF(S33<=VLOOKUP(K33,Valores!E:F,2,0),"Cumple","No cumple"))) -> Cumple | U33: =IFERROR(IF(T33="no cumple",S33-VLOOKUP(I33,Valores!$K$1:$L$4,2,0),0),S33-VLOOKUP(K33,Valores!E:F,2,0)) -> 0 | W33: 43114
A34: 46035 | B34: enero | C34: 100265 | D34: Venta | E34: Jonathan Enrique Pacheco Jimenez | F34: TECURECO-110 | G34: =IFERROR(VLOOKUP(F34,Productos!$A$2:$D$277,2,0)," ") -> Repisa Escritorio Caramelo x 110cm | H34: 1 | I34: =IFERROR(VLOOKUP(F34,Productos!$A$2:$D$277,3,0)," ") -> Repisa | J34: Bolívar | K34: Cartagena | L34: =IF(O34>0,"Despachado","En alistamiento") -> Despachado | M34: Coordinadora | N34: 4003635-84151486070 | O34: 46037 | P34: 46039 | Q34: =IF(P34>0,"Entregado","En transito") -> Entregado | R34: =IF(L34="Despachado",NETWORKDAYS.INTL(A34,O34,11,Valores!$A$2:$A$19)-1,"PTE") -> 2 | S34: =IF(Q34="Entregado",NETWORKDAYS.INTL(A34,P34,11,Valores!$A$2:$A$19)-1,"PTE") -> 4 | T34: =IF(Q34="Entregado",IFERROR(IF(I34=VLOOKUP(I34,Valores!$K$1:$K$4,1,0),IF(S34<=VLOOKUP(I34,Valores!$K$1:$L$4,2,0),"Cumple","No cumple")),IF(S34<=VLOOKUP(K34,Valores!E:F,2,0),"Cumple","No cumple"))) -> Cumple | U34: =IFERROR(IF(T34="no cumple",S34-VLOOKUP(I34,Valores!$K$1:$L$4,2,0),0),S34-VLOOKUP(K34,Valores!E:F,2,0)) -> 0 | W34: 40669
A35: 46035 | B35: enero | C35: 100266 | D35: Venta | E35: Adriana Chavarro | F35: TECUTFE6C-80 | G35: =IFERROR(VLOOKUP(F35,Productos!$A$2:$D$277,2,0)," ") -> Superficie Escritorio Fresno Europeo 160x80 Clasico | H35: 1 | I35: =IFERROR(VLOOKUP(F35,Productos!$A$2:$D$277,3,0)," ") -> Superficie | J35: Bogotá y alrededores | K35: Bogotá | L35: =IF(O35>0,"Despachado","En alistamiento") -> Despachado | M35: Envía | N35: 4006959-954101371581 | O35: 46037 | P35: 46038 | Q35: =IF(P35>0,"Entregado","En transito") -> Entregado | R35: =IF(L35="Despachado",NETWORKDAYS.INTL(A35,O35,11,Valores!$A$2:$A$19)-1,"PTE") -> 2 | S35: =IF(Q35="Entregado",NETWORKDAYS.INTL(A35,P35,11,Valores!$A$2:$A$19)-1,"PTE") -> 3 | T35: =IF(Q35="Entregado",IFERROR(IF(I35=VLOOKUP(I35,Valores!$K$1:$K$4,1,0),IF(S35<=VLOOKUP(I35,Valores!$K$1:$L$4,2,0),"Cumple","No cumple")),IF(S35<=VLOOKUP(K35,Valores!E:F,2,0),"Cumple","No cumple"))) -> Cumple | U35: =IFERROR(IF(T35="no cumple",S35-VLOOKUP(I35,Valores!$K$1:$L$4,2,0),0),S35-VLOOKUP(K35,Valores!E:F,2,0)) -> 0 | W35: 34487
A36: 46035 | B36: enero | C36: 100266 | D36: Venta | E36: Adriana Chavarro | F36: TECU3FBRO | G36: =IFERROR(VLOOKUP(F36,Productos!$A$2:$D$277,2,0)," ") -> Electric Standing Desk PRO Blanco | H36: 1 | I36: =IFERROR(VLOOKUP(F36,Productos!$A$2:$D$277,3,0)," ") -> Standing Desk | J36: Bogotá y alrededores | K36: Bogotá | L36: =IF(O36>0,"Despachado","En alistamiento") -> Despachado | M36: Coordinadora | N36: 4006929-84151487326 | O36: 46037 | P36: 46038 | Q36: =IF(P36>0,"Entregado","En transito") -> Entregado | R36: =IF(L36="Despachado",NETWORKDAYS.INTL(A36,O36,11,Valores!$A$2:$A$19)-1,"PTE") -> 2 | S36: =IF(Q36="Entregado",NETWORKDAYS.INTL(A36,P36,11,Valores!$A$2:$A$19)-1,"PTE") -> 3 | T36: =IF(Q36="Entregado",IFERROR(IF(I36=VLOOKUP(I36,Valores!$K$1:$K$4,1,0),IF(S36<=VLOOKUP(I36,Valores!$K$1:$L$4,2,0),"Cumple","No cumple")),IF(S36<=VLOOKUP(K36,Valores!E:F,2,0),"Cumple","No cumple"))) -> Cumple | U36: =IFERROR(IF(T36="no cumple",S36-VLOOKUP(I36,Valores!$K$1:$L$4,2,0),0),S36-VLOOKUP(K36,Valores!E:F,2,0)) -> 0 | W36: 44550
A37: 46036 | B37: enero | C37: 100267 | D37: Venta | E37: EFRALU SAS / DANIEL GARCIA | F37: TECUTLCCS | G37: =IFERROR(VLOOKUP(F37,Productos!$A$2:$D$277,2,0)," ") -> Superficie en L Caramelo 180x150cm x 70 | H37: 1 | I37: =IFERROR(VLOOKUP(F37,Productos!$A$2:$D$277,3,0)," ") -> Superficie | J37: Bogotá y alrededores | K37: Bogotá | L37: =IF(O37>0,"Despachado","En alistamiento") -> Despachado | M37: Envía | N37: 4010031-954101372531 | O37: 46038 | P37: 46039 | Q37: =IF(P37>0,"Entregado","En transito") -> Entregado | R37: =IF(L37="Despachado",NETWORKDAYS.INTL(A37,O37,11,Valores!$A$2:$A$19)-1,"PTE") -> 2 | S37: =IF(Q37="Entregado",NETWORKDAYS.INTL(A37,P37,11,Valores!$A$2:$A$19)-1,"PTE") -> 3 | T37: =IF(Q37="Entregado",IFERROR(IF(I37=VLOOKUP(I37,Valores!$K$1:$K$4,1,0),IF(S37<=VLOOKUP(I37,Valores!$K$1:$L$4,2,0),"Cumple","No cumple")),IF(S37<=VLOOKUP(K37,Valores!E:F,2,0),"Cumple","No cumple"))) -> Cumple | U37: =IFERROR(IF(T37="no cumple",S37-VLOOKUP(I37,Valores!$K$1:$L$4,2,0),0),S37-VLOOKUP(K37,Valores!E:F,2,0)) -> 0 | W37: 36093
A38: 46036 | B38: enero | C38: 100267 | D38: Venta | E38: EFRALU SAS / DANIEL GARCIA | F38: TECULFN2 | G38: =IFERROR(VLOOKUP(F38,Productos!$A$2:$D$277,2,0)," ") -> Electric Standing Desk En L Frame Negro 2.0 | H38: 1 | I38: =IFERROR(VLOOKUP(F38,Productos!$A$2:$D$277,3,0)," ") -> Standing Desk | J38: Bogotá y alrededores | K38: Bogotá | L38: =IF(O38>0,"Despachado","En alistamiento") -> Despachado | M38: Coordinadora | N38: 4009949-84151488583 | O38: 46038 | P38: 46041 | Q38: =IF(P38>0,"Entregado","En transito") -> Entregado | R38: =IF(L38="Despachado",NETWORKDAYS.INTL(A38,O38,11,Valores!$A$2:$A$19)-1,"PTE") -> 2 | S38: =IF(Q38="Entregado",NETWORKDAYS.INTL(A38,P38,11,Valores!$A$2:$A$19)-1,"PTE") -> 4 | T38: =IF(Q38="Entregado",IFERROR(IF(I38=VLOOKUP(I38,Valores!$K$1:$K$4,1,0),IF(S38<=VLOOKUP(I38,Valores!$K$1:$L$4,2,0),"Cumple","No cumple")),IF(S38<=VLOOKUP(K38,Valores!E:F,2,0),"Cumple","No cumple"))) -> No cumple | U38: =IFERROR(IF(T38="no cumple",S38-VLOOKUP(I38,Valores!$K$1:$L$4,2,0),0),S38-VLOOKUP(K38,Valores!E:F,2,0)) -> 1 | V38: Transporte | W38: 65353 | Y38: Demora en entrega
A39: 46036 | B39: enero | C39: 100267 | D39: Venta | E39: EFRALU SAS / DANIEL GARCIA | F39: TECU2CBC-77 | G39: =IFERROR(VLOOKUP(F39,Productos!$A$2:$D$277,2,0)," ") -> Cajonero 2.0 Bicolor Caramelo x77cm | H39: 1 | I39: =IFERROR(VLOOKUP(F39,Productos!$A$2:$D$277,3,0)," ") -> Archivador | J39: Bogotá y alrededores | K39: Bogotá | L39: =IF(O39>0,"Despachado","En alistamiento") -> Despachado | M39: Envía | N39: 4034508-954101379327 | O39: 46048 | P39: 46049 | Q39: =IF(P39>0,"Entregado","En transito") -> Entregado | R39: =IF(L39="Despachado",NETWORKDAYS.INTL(A39,O39,11,Valores!$A$2:$A$19)-1,"PTE") -> 10 | S39: =IF(Q39="Entregado",NETWORKDAYS.INTL(A39,P39,11,Valores!$A$2:$A$19)-1,"PTE") -> 11 | T39: =IF(Q39="Entregado",IFERROR(IF(I39=VLOOKUP(I39,Valores!$K$1:$K$4,1,0),IF(S39<=VLOOKUP(I39,Valores!$K$1:$L$4,2,0),"Cumple","No cumple")),IF(S39<=VLOOKUP(K39,Valores!E:F,2,0),"Cumple","No cumple"))) -> No cumple | U39: =IFERROR(IF(T39="no cumple",S39-VLOOKUP(I39,Valores!$K$1:$L$4,2,0),0),S39-VLOOKUP(K39,Valores!E:F,2,0)) -> 6 | V39: Producción | W39: 67823 | Y39: Disponibilidad materia prima
A40: 46036 | B40: enero | C40: 100268 | D40: Venta | E40: Nicolas Patiño Cañas | F40: TECUCT | G40: =IFERROR(VLOOKUP(F40,Productos!$A$2:$D$277,2,0)," ") -> Bandeja de cables | H40: 1 | I40: =IFERROR(VLOOKUP(F40,Productos!$A$2:$D$277,3,0)," ") -> Accesorio | J40: Bogotá y alrededores | K40: Bogotá | L40: =IF(O40>0,"Despachado","En alistamiento") -> Despachado | M40: Coordinadora | N40: 4029581-84151495795 | O40: 46045 | P40: 46048 | Q40: =IF(P40>0,"Entregado","En transito") -> Entregado | R40: =IF(L40="Despachado",NETWORKDAYS.INTL(A40,O40,11,Valores!$A$2:$A$19)-1,"PTE") -> 8 | S40: =IF(Q40="Entregado",NETWORKDAYS.INTL(A40,P40,11,Valores!$A$2:$A$19)-1,"PTE") -> 10 | T40: =IF(Q40="Entregado",IFERROR(IF(I40=VLOOKUP(I40,Valores!$K$1:$K$4,1,0),IF(S40<=VLOOKUP(I40,Valores!$K$1:$L$4,2,0),"Cumple","No cumple")),IF(S40<=VLOOKUP(K40,Valores!E:F,2,0),"Cumple","No cumple"))) -> No cumple | U40: =IFERROR(IF(T40="no cumple",S40-VLOOKUP(I40,Valores!$K$1:$L$4,2,0),0),S40-VLOOKUP(K40,Valores!E:F,2,0)) -> 7 | V40: Producción | W40: 26681 | Y40: Demora en proceso de producción
A41: 46036 | B41: enero | C41: 100268 | D41: Venta | E41: Nicolas Patiño Cañas | F41: TECUAN | G41: =IFERROR(VLOOKUP(F41,Productos!$A$2:$D$277,2,0)," ") -> Archivador TECU Negro | H41: 1 | I41: =IFERROR(VLOOKUP(F41,Productos!$A$2:$D$277,3,0)," ") -> Archivador | J41: Bogotá y alrededores | K41: Bogotá | L41: =IF(O41>0,"Despachado","En alistamiento") -> Despachado | M41: Envía | N41: 4029587-954101377984 | O41: 46045 | P41: 46046 | Q41: =IF(P41>0,"Entregado","En transito") -> Entregado | R41: =IF(L41="Despachado",NETWORKDAYS.INTL(A41,O41,11,Valores!$A$2:$A$19)-1,"PTE") -> 8 | S41: =IF(Q41="Entregado",NETWORKDAYS.INTL(A41,P41,11,Valores!$A$2:$A$19)-1,"PTE") -> 9 | T41: =IF(Q41="Entregado",IFERROR(IF(I41=VLOOKUP(I41,Valores!$K$1:$K$4,1,0),IF(S41<=VLOOKUP(I41,Valores!$K$1:$L$4,2,0),"Cumple","No cumple")),IF(S41<=VLOOKUP(K41,Valores!E:F,2,0),"Cumple","No cumple"))) -> No cumple | U41: =IFERROR(IF(T41="no cumple",S41-VLOOKUP(I41,Valores!$K$1:$L$4,2,0),0),S41-VLOOKUP(K41,Valores!E:F,2,0)) -> 4 | V41: Producción | W41: 57135 | Y41: Demora en proceso de producción
A42: 46037 | B42: enero | C42: 100269 | D42: Venta | E42: Juan Mayorga | F42: TECUTRM5C | G42: =IFERROR(VLOOKUP(F42,Productos!$A$2:$D$277,2,0)," ") -> Superficie Roble Miel 150x75 Clasico | H42: 1 | I42: =IFERROR(VLOOKUP(F42,Productos!$A$2:$D$277,3,0)," ") -> Superficie | J42: Antioquia | K42: El Retiro | L42: =IF(O42>0,"Despachado","En alistamiento") -> Despachado | M42: Envía | N42: 4034783-954101379381 | O42: 46048 | P42: 46050 | Q42: =IF(P42>0,"Entregado","En transito") -> Entregado | R42: =IF(L42="Despachado",NETWORKDAYS.INTL(A42,O42,11,Valores!$A$2:$A$19)-1,"PTE") -> 9 | S42: =IF(Q42="Entregado",NETWORKDAYS.INTL(A42,P42,11,Valores!$A$2:$A$19)-1,"PTE") -> 11 | T42: =IF(Q42="Entregado",IFERROR(IF(I42=VLOOKUP(I42,Valores!$K$1:$K$4,1,0),IF(S42<=VLOOKUP(I42,Valores!$K$1:$L$4,2,0),"Cumple","No cumple")),IF(S42<=VLOOKUP(K42,Valores!E:F,2,0),"Cumple","No cumple"))) -> No cumple | U42: =IFERROR(IF(T42="no cumple",S42-VLOOKUP(I42,Valores!$K$1:$L$4,2,0),0),S42-VLOOKUP(K42,Valores!E:F,2,0)) -> 6 | V42: Producción | W42: 43778 | Y42: Demora en proceso de pintura | Z42: Mónica estuvo enferma y se hizo la presentación de los nuevos Productos.
A43: 46037 | B43: enero | C43: 100269 | D43: Venta | E43: Juan Mayorga | F43: TECU3FNPRO | G43: =IFERROR(VLOOKUP(F43,Productos!$A$2:$D$277,2,0)," ") -> Electric Standing Desk PRO Negro | H43: 1 | I43: =IFERROR(VLOOKUP(F43,Productos!$A$2:$D$277,3,0)," ") -> Standing Desk | J43: Antioquia | K43: El Retiro | L43: =IF(O43>0,"Despachado","En alistamiento") -> Despachado | M43: Coordinadora | N43: 4034782-84151497441 | O43: 46048 | P43: 46050 | Q43: =IF(P43>0,"Entregado","En transito") -> Entregado | R43: =IF(L43="Despachado",NETWORKDAYS.INTL(A43,O43,11,Valores!$A$2:$A$19)-1,"PTE") -> 9 | S43: =IF(Q43="Entregado",NETWORKDAYS.INTL(A43,P43,11,Valores!$A$2:$A$19)-1,"PTE") -> 11 | T43: =IF(Q43="Entregado",IFERROR(IF(I43=VLOOKUP(I43,Valores!$K$1:$K$4,1,0),IF(S43<=VLOOKUP(I43,Valores!$K$1:$L$4,2,0),"Cumple","No cumple")),IF(S43<=VLOOKUP(K43,Valores!E:F,2,0),"Cumple","No cumple"))) -> No cumple | U43: =IFERROR(IF(T43="no cumple",S43-VLOOKUP(I43,Valores!$K$1:$L$4,2,0),0),S43-VLOOKUP(K43,Valores!E:F,2,0)) -> 6 | V43: Producción | W43: 44550 | Y43: Demora en proceso de pintura
A44: 46037 | B44: enero | C44: 100269 | D44: Venta | E44: Juan Mayorga | F44: TECUCT | G44: =IFERROR(VLOOKUP(F44,Productos!$A$2:$D$277,2,0)," ") -> Bandeja de cables | H44: 1 | I44: =IFERROR(VLOOKUP(F44,Productos!$A$2:$D$277,3,0)," ") -> Accesorio | J44: Antioquia | K44: El Retiro | L44: =IF(O44>0,"Despachado","En alistamiento") -> Despachado | M44: Coordinadora | N44: 4035535-84151497669 | O44: 46048 | P44: 46049 | Q44: =IF(P44>0,"Entregado","En transito") -> Entregado | R44: =IF(L44="Despachado",NETWORKDAYS.INTL(A44,O44,11,Valores!$A$2:$A$19)-1,"PTE") -> 9 | S44: =IF(Q44="Entregado",NETWORKDAYS.INTL(A44,P44,11,Valores!$A$2:$A$19)-1,"PTE") -> 10 | T44: =IF(Q44="Entregado",IFERROR(IF(I44=VLOOKUP(I44,Valores!$K$1:$K$4,1,0),IF(S44<=VLOOKUP(I44,Valores!$K$1:$L$4,2,0),"Cumple","No cumple")),IF(S44<=VLOOKUP(K44,Valores!E:F,2,0),"Cumple","No cumple"))) -> No cumple | U44: =IFERROR(IF(T44="no cumple",S44-VLOOKUP(I44,Valores!$K$1:$L$4,2,0),0),S44-VLOOKUP(K44,Valores!E:F,2,0)) -> 5 | V44: Producción | W44: 25733 | Y44: Demora en proceso de pintura
A45: 46039 | B45: enero | C45: 100270 | D45: Venta | E45: Manuel Dover | F45: TECUTLFES | G45: =IFERROR(VLOOKUP(F45,Productos!$A$2:$D$277,2,0)," ") -> Superficie en L Fresno 180x150cm x 70 | H45: 1 | I45: =IFERROR(VLOOKUP(F45,Productos!$A$2:$D$277,3,0)," ") -> Superficie | J45: Antioquia | K45: Medellín | L45: =IF(O45>0,"Despachado","En alistamiento") -> Despachado | M45: Envía | N45: 4019717-954101375226 | O45: 46042 | P45: 46043 | Q45: =IF(P45>0,"Entregado","En transito") -> Entregado | R45: =IF(L45="Despachado",NETWORKDAYS.INTL(A45,O45,11,Valores!$A$2:$A$19)-1,"PTE") -> 2 | S45: =IF(Q45="Entregado",NETWORKDAYS.INTL(A45,P45,11,Valores!$A$2:$A$19)-1,"PTE") -> 3 | T45: =IF(Q45="Entregado",IFERROR(IF(I45=VLOOKUP(I45,Valores!$K$1:$K$4,1,0),IF(S45<=VLOOKUP(I45,Valores!$K$1:$L$4,2,0),"Cumple","No cumple")),IF(S45<=VLOOKUP(K45,Valores!E:F,2,0),"Cumple","No cumple"))) -> Cumple | U45: =IFERROR(IF(T45="no cumple",S45-VLOOKUP(I45,Valores!$K$1:$L$4,2,0),0),S45-VLOOKUP(K45,Valores!E:F,2,0)) -> 0 | W45: 39235
A46: 46039 | B46: enero | C46: 100270 | D46: Venta | E46: Manuel Dover | F46: TECULFN2 | G46: =IFERROR(VLOOKUP(F46,Productos!$A$2:$D$277,2,0)," ") -> Electric Standing Desk En L Frame Negro 2.0 | H46: 1 | I46: =IFERROR(VLOOKUP(F46,Productos!$A$2:$D$277,3,0)," ") -> Standing Desk | J46: Antioquia | K46: Medellín | L46: =IF(O46>0,"Despachado","En alistamiento") -> Despachado | M46: Coordinadora | N46: 4020156-84151492428 | O46: 46042 | P46: 46050 | Q46: =IF(P46>0,"Entregado","En transito") -> Entregado | R46: =IF(L46="Despachado",NETWORKDAYS.INTL(A46,O46,11,Valores!$A$2:$A$19)-1,"PTE") -> 2 | S46: =IF(Q46="Entregado",NETWORKDAYS.INTL(A46,P46,11,Valores!$A$2:$A$19)-1,"PTE") -> 9 | T46: =IF(Q46="Entregado",IFERROR(IF(I46=VLOOKUP(I46,Valores!$K$1:$K$4,1,0),IF(S46<=VLOOKUP(I46,Valores!$K$1:$L$4,2,0),"Cumple","No cumple")),IF(S46<=VLOOKUP(K46,Valores!E:F,2,0),"Cumple","No cumple"))) -> No cumple | U46: =IFERROR(IF(T46="no cumple",S46-VLOOKUP(I46,Valores!$K$1:$L$4,2,0),0),S46-VLOOKUP(K46,Valores!E:F,2,0)) -> 6 | V46: Cliente | W46: 65353 | Y46: Ausencia del cliente | Z46: Se hicieron 2 intentos de entrega, se generó novedad, se realizó pago adicional.
A47: 46042 | B47: enero | C47: 100272 | D47: Venta | E47: Camilo Ramírez | F47: TECU2FNG | G47: =IFERROR(VLOOKUP(F47,Productos!$A$2:$D$277,2,0)," ") -> Electric Standing Desk GO Negro | H47: 1 | I47: =IFERROR(VLOOKUP(F47,Productos!$A$2:$D$277,3,0)," ") -> Standing Desk | J47: Antioquia | K47: Itagui | L47: =IF(O47>0,"Despachado","En alistamiento") -> Despachado | M47: Coordinadora | N47: 4023156-84151493557 | O47: 46043 | P47: 46044 | Q47: =IF(P47>0,"Entregado","En transito") -> Entregado | R47: =IF(L47="Despachado",NETWORKDAYS.INTL(A47,O47,11,Valores!$A$2:$A$19)-1,"PTE") -> 1 | S47: =IF(Q47="Entregado",NETWORKDAYS.INTL(A47,P47,11,Valores!$A$2:$A$19)-1,"PTE") -> 2 | T47: =IF(Q47="Entregado",IFERROR(IF(I47=VLOOKUP(I47,Valores!$K$1:$K$4,1,0),IF(S47<=VLOOKUP(I47,Valores!$K$1:$L$4,2,0),"Cumple","No cumple")),IF(S47<=VLOOKUP(K47,Valores!E:F,2,0),"Cumple","No cumple"))) -> Cumple | U47: =IFERROR(IF(T47="no cumple",S47-VLOOKUP(I47,Valores!$K$1:$L$4,2,0),0),S47-VLOOKUP(K47,Valores!E:F,2,0)) -> 0 | W47: 33316
A48: 46042 | B48: enero | C48: 100272 | D48: Venta | E48: Camilo Ramírez | F48: TECUTRN2C-60 | G48: =IFERROR(VLOOKUP(F48,Productos!$A$2:$D$277,2,0)," ") -> Superficie Escritorio Roble Negro 120x60 Clasico Small | H48: 1 | I48: =IFERROR(VLOOKUP(F48,Productos!$A$2:$D$277,3,0)," ") -> Superficie | J48: Antioquia | K48: Itagui | L48: =IF(O48>0,"Despachado","En alistamiento") -> Despachado | M48: Coordinadora | N48: 4023155-84151493556 | O48: 46043 | P48: 46045 | Q48: =IF(P48>0,"Entregado","En transito") -> Entregado | R48: =IF(L48="Despachado",NETWORKDAYS.INTL(A48,O48,11,Valores!$A$2:$A$19)-1,"PTE") -> 1 | S48: =IF(Q48="Entregado",NETWORKDAYS.INTL(A48,P48,11,Valores!$A$2:$A$19)-1,"PTE") -> 3 | T48: =IF(Q48="Entregado",IFERROR(IF(I48=VLOOKUP(I48,Valores!$K$1:$K$4,1,0),IF(S48<=VLOOKUP(I48,Valores!$K$1:$L$4,2,0),"Cumple","No cumple")),IF(S48<=VLOOKUP(K48,Valores!E:F,2,0),"Cumple","No cumple"))) -> Cumple | U48: =IFERROR(IF(T48="no cumple",S48-VLOOKUP(I48,Valores!$K$1:$L$4,2,0),0),S48-VLOOKUP(K48,Valores!E:F,2,0)) -> 0 | W48: 43114
A49: 46043 | B49: enero | C49: 100273 | D49: Venta | E49: Oscar Yonda | F49: TECUTFE7C | G49: =IFERROR(VLOOKUP(F49,Productos!$A$2:$D$277,2,0)," ") -> Superficie Fresno Europeo 170x70 Clasico | H49: 1 | I49: =IFERROR(VLOOKUP(F49,Productos!$A$2:$D$277,3,0)," ") -> Superficie | J49: Valle del Cauca | K49: Cali | L49: =IF(O49>0,"Despachado","En alistamiento") -> Despachado | M49: Envía | N49: 4039854-954101380568 | O49: 46049 | P49: 46050 | Q49: =IF(P49>0,"Entregado","En transito") -> Entregado | R49: =IF(L49="Despachado",NETWORKDAYS.INTL(A49,O49,11,Valores!$A$2:$A$19)-1,"PTE") -> 5 | S49: =IF(Q49="Entregado",NETWORKDAYS.INTL(A49,P49,11,Valores!$A$2:$A$19)-1,"PTE") -> 6 | T49: =IF(Q49="Entregado",IFERROR(IF(I49=VLOOKUP(I49,Valores!$K$1:$K$4,1,0),IF(S49<=VLOOKUP(I49,Valores!$K$1:$L$4,2,0),"Cumple","No cumple")),IF(S49<=VLOOKUP(K49,Valores!E:F,2,0),"Cumple","No cumple"))) -> No cumple | U49: =IFERROR(IF(T49="no cumple",S49-VLOOKUP(I49,Valores!$K$1:$L$4,2,0),0),S49-VLOOKUP(K49,Valores!E:F,2,0)) -> 3 | V49: Producción | W49: 35290 | Y49: Demora en proceso de producción
A50: 46043 | B50: enero | C50: 100273 | D50: Venta | E50: Oscar Yonda | F50: TECU2FNG | G50: =IFERROR(VLOOKUP(F50,Productos!$A$2:$D$277,2,0)," ") -> Electric Standing Desk GO Negro | H50: 1 | I50: =IFERROR(VLOOKUP(F50,Productos!$A$2:$D$277,3,0)," ") -> Standing Desk | J50: Valle del Cauca | K50: Cali | L50: =IF(O50>0,"Despachado","En alistamiento") -> Despachado | M50: Coordinadora | N50: 4040567-84151499561 | O50: 46049 | P50: 46050 | Q50: =IF(P50>0,"Entregado","En transito") -> Entregado | R50: =IF(L50="Despachado",NETWORKDAYS.INTL(A50,O50,11,Valores!$A$2:$A$19)-1,"PTE") -> 5 | S50: =IF(Q50="Entregado",NETWORKDAYS.INTL(A50,P50,11,Valores!$A$2:$A$19)-1,"PTE") -> 6 | T50: =IF(Q50="Entregado",IFERROR(IF(I50=VLOOKUP(I50,Valores!$K$1:$K$4,1,0),IF(S50<=VLOOKUP(I50,Valores!$K$1:$L$4,2,0),"Cumple","No cumple")),IF(S50<=VLOOKUP(K50,Valores!E:F,2,0),"Cumple","No cumple"))) -> No cumple | U50: =IFERROR(IF(T50="no cumple",S50-VLOOKUP(I50,Valores!$K$1:$L$4,2,0),0),S50-VLOOKUP(K50,Valores!E:F,2,0)) -> 3 | V50: Producción | W50: 43114 | Y50: Demora en proceso de producción
A51: 46043 | B51: enero | C51: 100274 | D51: Venta | E51: Deiner Y. Muñoz D. | F51: TECUTFE2C | G51: =IFERROR(VLOOKUP(F51,Productos!$A$2:$D$277,2,0)," ") -> Superficie Fresno Europeo 120x70 Clasico Small | H51: 1 | I51: =IFERROR(VLOOKUP(F51,Productos!$A$2:$D$277,3,0)," ") -> Superficie | J51: Bogotá y alrededores | K51: Bogotá | L51: =IF(O51>0,"Despachado","En alistamiento") -> Despachado | M51: Coordinadora | N51: 4036553-84151498115 | O51: 46048 | P51: 46051 | Q51: =IF(P51>0,"Entregado","En transito") -> Entregado | R51: =IF(L51="Despachado",NETWORKDAYS.INTL(A51,O51,11,Valores!$A$2:$A$19)-1,"PTE") -> 4 | S51: =IF(Q51="Entregado",NETWORKDAYS.INTL(A51,P51,11,Valores!$A$2:$A$19)-1,"PTE") -> 7 | T51: =IF(Q51="Entregado",IFERROR(IF(I51=VLOOKUP(I51,Valores!$K$1:$K$4,1,0),IF(S51<=VLOOKUP(I51,Valores!$K$1:$L$4,2,0),"Cumple","No cumple")),IF(S51<=VLOOKUP(K51,Valores!E:F,2,0),"Cumple","No cumple"))) -> No cumple | U51: =IFERROR(IF(T51="no cumple",S51-VLOOKUP(I51,Valores!$K$1:$L$4,2,0),0),S51-VLOOKUP(K51,Valores!E:F,2,0)) -> 4 | V51: Producción - Transporte | W51: 25952 | Y51: Demora en proceso de producción- Novedad en el reparto | Z51: Se debía pintar la bandeja de la repisa
A52: 46043 | B52: enero | C52: 100274 | D52: Venta | E52: Deiner Y. Muñoz D. | F52: TECUREFE -80 | G52: =IFERROR(VLOOKUP(F52,Productos!$A$2:$D$277,2,0)," ") -> Repisa Escritorio Fresno Europeo x 80cm | H52: 1 | I52: =IFERROR(VLOOKUP(F52,Productos!$A$2:$D$277,3,0)," ") -> Repisa | J52: Bogotá y alrededores | K52: Bogotá | L52: =IF(O52>0,"Despachado","En alistamiento") -> Despachado | M52: Coordinadora | N52: 4036553-84151498115 | O52: 46048 | P52: 46051 | Q52: =IF(P52>0,"Entregado","En transito") -> Entregado | R52: =IF(L52="Despachado",NETWORKDAYS.INTL(A52,O52,11,Valores!$A$2:$A$19)-1,"PTE") -> 4 | S52: =IF(Q52="Entregado",NETWORKDAYS.INTL(A52,P52,11,Valores!$A$2:$A$19)-1,"PTE") -> 7 | T52: =IF(Q52="Entregado",IFERROR(IF(I52=VLOOKUP(I52,Valores!$K$1:$K$4,1,0),IF(S52<=VLOOKUP(I52,Valores!$K$1:$L$4,2,0),"Cumple","No cumple")),IF(S52<=VLOOKUP(K52,Valores!E:F,2,0),"Cumple","No cumple"))) -> No cumple | U52: =IFERROR(IF(T52="no cumple",S52-VLOOKUP(I52,Valores!$K$1:$L$4,2,0),0),S52-VLOOKUP(K52,Valores!E:F,2,0)) -> 4 | V52: Producción - Transporte | W52: 0 | Y52: Demora en proceso de producción
A53: 46043 | B53: enero | C53: 100274 | D53: Venta | E53: Deiner Y. Muñoz D. | F53: TECU2FNG | G53: =IFERROR(VLOOKUP(F53,Productos!$A$2:$D$277,2,0)," ") -> Electric Standing Desk GO Negro | H53: 1 | I53: =IFERROR(VLOOKUP(F53,Productos!$A$2:$D$277,3,0)," ") -> Standing Desk | J53: Bogotá y alrededores | K53: Bogotá | L53: =IF(O53>0,"Despachado","En alistamiento") -> Despachado | M53: Coordinadora | N53: 4036552-84151498114 | O53: 46048 | P53: 46049 | Q53: =IF(P53>0,"Entregado","En transito") -> Entregado | R53: =IF(L53="Despachado",NETWORKDAYS.INTL(A53,O53,11,Valores!$A$2:$A$19)-1,"PTE") -> 4 | S53: =IF(Q53="Entregado",NETWORKDAYS.INTL(A53,P53,11,Valores!$A$2:$A$19)-1,"PTE") -> 5 | T53: =IF(Q53="Entregado",IFERROR(IF(I53=VLOOKUP(I53,Valores!$K$1:$K$4,1,0),IF(S53<=VLOOKUP(I53,Valores!$K$1:$L$4,2,0),"Cumple","No cumple")),IF(S53<=VLOOKUP(K53,Valores!E:F,2,0),"Cumple","No cumple"))) -> No cumple | U53: =IFERROR(IF(T53="no cumple",S53-VLOOKUP(I53,Valores!$K$1:$L$4,2,0),0),S53-VLOOKUP(K53,Valores!E:F,2,0)) -> 2 | V53: Producción | W53: 43114 | Y53: Demora en proceso de pintura
A54: 46043 | B54: enero | C54: 100274 | D54: Venta | E54: Deiner Y. Muñoz D. | F54: TECUCT | G54: =IFERROR(VLOOKUP(F54,Productos!$A$2:$D$277,2,0)," ") -> Bandeja de cables | H54: 1 | I54: =IFERROR(VLOOKUP(F54,Productos!$A$2:$D$277,3,0)," ") -> Accesorio | J54: Bogotá y alrededores | K54: Bogotá | L54: =IF(O54>0,"Despachado","En alistamiento") -> Despachado | M54: Coordinadora | N54: 4036376-84151498030 | O54: 46048 | P54: 46049 | Q54: =IF(P54>0,"Entregado","En transito") -> Entregado | R54: =IF(L54="Despachado",NETWORKDAYS.INTL(A54,O54,11,Valores!$A$2:$A$19)-1,"PTE") -> 4 | S54: =IF(Q54="Entregado",NETWORKDAYS.INTL(A54,P54,11,Valores!$A$2:$A$19)-1,"PTE") -> 5 | T54: =IF(Q54="Entregado",IFERROR(IF(I54=VLOOKUP(I54,Valores!$K$1:$K$4,1,0),IF(S54<=VLOOKUP(I54,Valores!$K$1:$L$4,2,0),"Cumple","No cumple")),IF(S54<=VLOOKUP(K54,Valores!E:F,2,0),"Cumple","No cumple"))) -> No cumple | U54: =IFERROR(IF(T54="no cumple",S54-VLOOKUP(I54,Valores!$K$1:$L$4,2,0),0),S54-VLOOKUP(K54,Valores!E:F,2,0)) -> 2 | V54: Producción | W54: 26681 | Y54: Demora en proceso de pintura
A55: 46044 | B55: enero | C55: 100275 | D55: Venta | E55: EFRALU SAS / DANIEL GARCIA | F55: TECUCT | G55: =IFERROR(VLOOKUP(F55,Productos!$A$2:$D$277,2,0)," ") -> Bandeja de cables | H55: 1 | I55: =IFERROR(VLOOKUP(F55,Productos!$A$2:$D$277,3,0)," ") -> Accesorio | J55: Bogotá y alrededores | K55: Bogotá | L55: =IF(O55>0,"Despachado","En alistamiento") -> Despachado | M55: Coordinadora | N55: 4026563-84151494908 | O55: 46044 | P55: 46045 | Q55: =IF(P55>0,"Entregado","En transito") -> Entregado | R55: =IF(L55="Despachado",NETWORKDAYS.INTL(A55,O55,11,Valores!$A$2:$A$19)-1,"PTE") -> 0 | S55: =IF(Q55="Entregado",NETWORKDAYS.INTL(A55,P55,11,Valores!$A$2:$A$19)-1,"PTE") -> 1 | T55: =IF(Q55="Entregado",IFERROR(IF(I55=VLOOKUP(I55,Valores!$K$1:$K$4,1,0),IF(S55<=VLOOKUP(I55,Valores!$K$1:$L$4,2,0),"Cumple","No cumple")),IF(S55<=VLOOKUP(K55,Valores!E:F,2,0),"Cumple","No cumple"))) -> Cumple | U55: =IFERROR(IF(T55="no cumple",S55-VLOOKUP(I55,Valores!$K$1:$L$4,2,0),0),S55-VLOOKUP(K55,Valores!E:F,2,0)) -> 0 | W55: 26681
A56: 46049 | B56: enero | C56: 100276 | D56: Venta | E56: Álvaro Ramírez Cardona | F56: TECU3FNPRO | G56: =IFERROR(VLOOKUP(F56,Productos!$A$2:$D$277,2,0)," ") -> Electric Standing Desk PRO Negro | H56: 1 | I56: =IFERROR(VLOOKUP(F56,Productos!$A$2:$D$277,3,0)," ") -> Standing Desk | J56: Antioquia | K56: Copacabana | L56: =IF(O56>0,"Despachado","En alistamiento") -> Despachado | M56: Coordinadora | N56: 4040057-84151499341 | O56: 46049 | P56: 46066 | Q56: =IF(P56>0,"Entregado","En transito") -> Entregado | R56: =IF(L56="Despachado",NETWORKDAYS.INTL(A56,O56,11,Valores!$A$2:$A$19)-1,"PTE") -> 0 | S56: =IF(Q56="Entregado",NETWORKDAYS.INTL(A56,P56,11,Valores!$A$2:$A$19)-1,"PTE") -> 15 | T56: =IF(Q56="Entregado",IFERROR(IF(I56=VLOOKUP(I56,Valores!$K$1:$K$4,1,0),IF(S56<=VLOOKUP(I56,Valores!$K$1:$L$4,2,0),"Cumple","No cumple")),IF(S56<=VLOOKUP(K56,Valores!E:F,2,0),"Cumple","No cumple"))) -> No cumple | U56: =IFERROR(IF(T56="no cumple",S56-VLOOKUP(I56,Valores!$K$1:$L$4,2,0),0),S56-VLOOKUP(K56,Valores!E:F,2,0)) -> 10 | V56: Cliente | W56: 36550 | Y56: Ausencia del cliente | Z56: Cliente se demoró en recoger el envío en punto Droop de Coordinadora en Copacabana.
A57: 46051 | B57: enero | C57: 100277 | D57: Venta | E57: Esteban Davila Arias | F57: TECU3FNCRO | G57: =IFERROR(VLOOKUP(F57,Productos!$A$2:$D$277,2,0)," ") -> Electric Standing Desk PRO Negro circular | H57: 1 | I57: =IFERROR(VLOOKUP(F57,Productos!$A$2:$D$277,3,0)," ") -> Standing Desk | J57: Quindío | K57: Armenia | L57: =IF(O57>0,"Despachado","En alistamiento") -> Despachado | M57: Particular | N57: N/A | O57: 46051 | P57: 46051 | Q57: =IF(P57>0,"Entregado","En transito") -> Entregado | R57: =IF(L57="Despachado",NETWORKDAYS.INTL(A57,O57,11,Valores!$A$2:$A$19)-1,"PTE") -> 0 | S57: =IF(Q57="Entregado",NETWORKDAYS.INTL(A57,P57,11,Valores!$A$2:$A$19)-1,"PTE") -> 0 | T57: =IF(Q57="Entregado",IFERROR(IF(I57=VLOOKUP(I57,Valores!$K$1:$K$4,1,0),IF(S57<=VLOOKUP(I57,Valores!$K$1:$L$4,2,0),"Cumple","No cumple")),IF(S57<=VLOOKUP(K57,Valores!E:F,2,0),"Cumple","No cumple"))) -> Cumple | U57: =IFERROR(IF(T57="no cumple",S57-VLOOKUP(I57,Valores!$K$1:$L$4,2,0),0),S57-VLOOKUP(K57,Valores!E:F,2,0)) -> 0 | W57: 50000
A58: 46051 | B58: enero | C58: 100277 | D58: Venta | E58: Esteban Davila Arias | F58: TECU3FNCRO | G58: =IFERROR(VLOOKUP(F58,Productos!$A$2:$D$277,2,0)," ") -> Electric Standing Desk PRO Negro circular | H58: 1 | I58: =IFERROR(VLOOKUP(F58,Productos!$A$2:$D$277,3,0)," ") -> Standing Desk | J58: Quindío | K58: Armenia | L58: =IF(O58>0,"Despachado","En alistamiento") -> Despachado | M58: Particular | N58: N/A | O58: 46051 | P58: 46051 | Q58: =IF(P58>0,"Entregado","En transito") -> Entregado | R58: =IF(L58="Despachado",NETWORKDAYS.INTL(A58,O58,11,Valores!$A$2:$A$19)-1,"PTE") -> 0 | S58: =IF(Q58="Entregado",NETWORKDAYS.INTL(A58,P58,11,Valores!$A$2:$A$19)-1,"PTE") -> 0 | T58: =IF(Q58="Entregado",IFERROR(IF(I58=VLOOKUP(I58,Valores!$K$1:$K$4,1,0),IF(S58<=VLOOKUP(I58,Valores!$K$1:$L$4,2,0),"Cumple","No cumple")),IF(S58<=VLOOKUP(K58,Valores!E:F,2,0),"Cumple","No cumple"))) -> Cumple | U58: =IFERROR(IF(T58="no cumple",S58-VLOOKUP(I58,Valores!$K$1:$L$4,2,0),0),S58-VLOOKUP(K58,Valores!E:F,2,0)) -> 0 | W58: 0
A59: 46051 | B59: enero | C59: 100277 | D59: Venta | E59: Esteban Davila Arias | F59: TECUTCO5C | G59: =IFERROR(VLOOKUP(F59,Productos!$A$2:$D$277,2,0)," ") -> Superficie Caramelo 150x70 Clasico | H59: 1 | I59: =IFERROR(VLOOKUP(F59,Productos!$A$2:$D$277,3,0)," ") -> Superficie | J59: Quindío | K59: Armenia | L59: =IF(O59>0,"Despachado","En alistamiento") -> Despachado | M59: Particular | N59: N/A | O59: 46051 | P59: 46051 | Q59: =IF(P59>0,"Entregado","En transito") -> Entregado | R59: =IF(L59="Despachado",NETWORKDAYS.INTL(A59,O59,11,Valores!$A$2:$A$19)-1,"PTE") -> 0 | S59: =IF(Q59="Entregado",NETWORKDAYS.INTL(A59,P59,11,Valores!$A$2:$A$19)-1,"PTE") -> 0 | T59: =IF(Q59="Entregado",IFERROR(IF(I59=VLOOKUP(I59,Valores!$K$1:$K$4,1,0),IF(S59<=VLOOKUP(I59,Valores!$K$1:$L$4,2,0),"Cumple","No cumple")),IF(S59<=VLOOKUP(K59,Valores!E:F,2,0),"Cumple","No cumple"))) -> Cumple | U59: =IFERROR(IF(T59="no cumple",S59-VLOOKUP(I59,Valores!$K$1:$L$4,2,0),0),S59-VLOOKUP(K59,Valores!E:F,2,0)) -> 0 | W59: 0
A60: 46051 | B60: enero | C60: 100277 | D60: Venta | E60: Esteban Davila Arias | F60: TECUTCO5C | G60: =IFERROR(VLOOKUP(F60,Productos!$A$2:$D$277,2,0)," ") -> Superficie Caramelo 150x70 Clasico | H60: 1 | I60: =IFERROR(VLOOKUP(F60,Productos!$A$2:$D$277,3,0)," ") -> Superficie | J60: Quindío | K60: Armenia | L60: =IF(O60>0,"Despachado","En alistamiento") -> Despachado | M60: Particular | N60: N/A | O60: 46051 | P60: 46051 | Q60: =IF(P60>0,"Entregado","En transito") -> Entregado | R60: =IF(L60="Despachado",NETWORKDAYS.INTL(A60,O60,11,Valores!$A$2:$A$19)-1,"PTE") -> 0 | S60: =IF(Q60="Entregado",NETWORKDAYS.INTL(A60,P60,11,Valores!$A$2:$A$19)-1,"PTE") -> 0 | T60: =IF(Q60="Entregado",IFERROR(IF(I60=VLOOKUP(I60,Valores!$K$1:$K$4,1,0),IF(S60<=VLOOKUP(I60,Valores!$K$1:$L$4,2,0),"Cumple","No cumple")),IF(S60<=VLOOKUP(K60,Valores!E:F,2,0),"Cumple","No cumple"))) -> Cumple | U60: =IFERROR(IF(T60="no cumple",S60-VLOOKUP(I60,Valores!$K$1:$L$4,2,0),0),S60-VLOOKUP(K60,Valores!E:F,2,0)) -> 0 | W60: 0
A61: 46051 | B61: enero | C61: 100278 | D61: Venta | E61: Lucelly Ramos | F61: TECUTCO3C | G61: =IFERROR(VLOOKUP(F61,Productos!$A$2:$D$277,2,0)," ") -> Superficie Caramelo 130x70 Clasico | H61: 1 | I61: =IFERROR(VLOOKUP(F61,Productos!$A$2:$D$277,3,0)," ") -> Superficie | J61: Bogotá y alrededores | K61: Bogotá | L61: =IF(O61>0,"Despachado","En alistamiento") -> Despachado | M61: Coordinadora | N61: 4047906-84151502132 | O61: 46052 | P61: 46053 | Q61: =IF(P61>0,"Entregado","En transito") -> Entregado | R61: =IF(L61="Despachado",NETWORKDAYS.INTL(A61,O61,11,Valores!$A$2:$A$19)-1,"PTE") -> 1 | S61: =IF(Q61="Entregado",NETWORKDAYS.INTL(A61,P61,11,Valores!$A$2:$A$19)-1,"PTE") -> 2 | T61: =IF(Q61="Entregado",IFERROR(IF(I61=VLOOKUP(I61,Valores!$K$1:$K$4,1,0),IF(S61<=VLOOKUP(I61,Valores!$K$1:$L$4,2,0),"Cumple","No cumple")),IF(S61<=VLOOKUP(K61,Valores!E:F,2,0),"Cumple","No cumple"))) -> Cumple | U61: =IFERROR(IF(T61="no cumple",S61-VLOOKUP(I61,Valores!$K$1:$L$4,2,0),0),S61-VLOOKUP(K61,Valores!E:F,2,0)) -> 0 | W61: 25952
A62: 46051 | B62: enero | C62: 100278 | D62: Venta | E62: Lucelly Ramos | F62: TECUTBANTE | G62: =IFERROR(VLOOKUP(F62,Productos!$A$2:$D$277,2,0)," ") -> Bandeja de teclado | H62: 1 | I62: =IFERROR(VLOOKUP(F62,Productos!$A$2:$D$277,3,0)," ") -> Accesorio | J62: Bogotá y alrededores | K62: Bogotá | L62: =IF(O62>0,"Despachado","En alistamiento") -> Despachado | M62: Coordinadora | N62: 4047906-84151502132 | O62: 46052 | P62: 46053 | Q62: =IF(P62>0,"Entregado","En transito") -> Entregado | R62: =IF(L62="Despachado",NETWORKDAYS.INTL(A62,O62,11,Valores!$A$2:$A$19)-1,"PTE") -> 1 | S62: =IF(Q62="Entregado",NETWORKDAYS.INTL(A62,P62,11,Valores!$A$2:$A$19)-1,"PTE") -> 2 | T62: =IF(Q62="Entregado",IFERROR(IF(I62=VLOOKUP(I62,Valores!$K$1:$K$4,1,0),IF(S62<=VLOOKUP(I62,Valores!$K$1:$L$4,2,0),"Cumple","No cumple")),IF(S62<=VLOOKUP(K62,Valores!E:F,2,0),"Cumple","No cumple"))) -> Cumple | U62: =IFERROR(IF(T62="no cumple",S62-VLOOKUP(I62,Valores!$K$1:$L$4,2,0),0),S62-VLOOKUP(K62,Valores!E:F,2,0)) -> 0 | W62: 0
A63: 46051 | B63: enero | C63: 100278 | D63: Venta | E63: Lucelly Ramos | F63: TECU3FNPRO | G63: =IFERROR(VLOOKUP(F63,Productos!$A$2:$D$277,2,0)," ") -> Electric Standing Desk PRO Negro | H63: 1 | I63: =IFERROR(VLOOKUP(F63,Productos!$A$2:$D$277,3,0)," ") -> Standing Desk | J63: Bogotá y alrededores | K63: Bogotá | L63: =IF(O63>0,"Despachado","En alistamiento") -> Despachado | M63: Coordinadora | N63: 4047905-84151502131 | O63: 46052 | P63: 46053 | Q63: =IF(P63>0,"Entregado","En transito") -> Entregado | R63: =IF(L63="Despachado",NETWORKDAYS.INTL(A63,O63,11,Valores!$A$2:$A$19)-1,"PTE") -> 1 | S63: =IF(Q63="Entregado",NETWORKDAYS.INTL(A63,P63,11,Valores!$A$2:$A$19)-1,"PTE") -> 2 | T63: =IF(Q63="Entregado",IFERROR(IF(I63=VLOOKUP(I63,Valores!$K$1:$K$4,1,0),IF(S63<=VLOOKUP(I63,Valores!$K$1:$L$4,2,0),"Cumple","No cumple")),IF(S63<=VLOOKUP(K63,Valores!E:F,2,0),"Cumple","No cumple"))) -> Cumple | U63: =IFERROR(IF(T63="no cumple",S63-VLOOKUP(I63,Valores!$K$1:$L$4,2,0),0),S63-VLOOKUP(K63,Valores!E:F,2,0)) -> 0 | W63: 43114
A64: 46051 | B64: enero | C64: 100278 | D64: Venta | E64: Lucelly Ramos | F64: TECUCT | G64: =IFERROR(VLOOKUP(F64,Productos!$A$2:$D$277,2,0)," ") -> Bandeja de cables | H64: 1 | I64: =IFERROR(VLOOKUP(F64,Productos!$A$2:$D$277,3,0)," ") -> Accesorio | J64: Bogotá y alrededores | K64: Bogotá | L64: =IF(O64>0,"Despachado","En alistamiento") -> Despachado | M64: Coordinadora | N64: 4048555-84151502331 | O64: 46052 | P64: 46053 | Q64: =IF(P64>0,"Entregado","En transito") -> Entregado | R64: =IF(L64="Despachado",NETWORKDAYS.INTL(A64,O64,11,Valores!$A$2:$A$19)-1,"PTE") -> 1 | S64: =IF(Q64="Entregado",NETWORKDAYS.INTL(A64,P64,11,Valores!$A$2:$A$19)-1,"PTE") -> 2 | T64: =IF(Q64="Entregado",IFERROR(IF(I64=VLOOKUP(I64,Valores!$K$1:$K$4,1,0),IF(S64<=VLOOKUP(I64,Valores!$K$1:$L$4,2,0),"Cumple","No cumple")),IF(S64<=VLOOKUP(K64,Valores!E:F,2,0),"Cumple","No cumple"))) -> Cumple | U64: =IFERROR(IF(T64="no cumple",S64-VLOOKUP(I64,Valores!$K$1:$L$4,2,0),0),S64-VLOOKUP(K64,Valores!E:F,2,0)) -> 0 | W64: 26681
A65: 46051 | B65: enero | C65: 100278 | D65: Venta | E65: Lucelly Ramos | G65: Servicio Instalación | H65: 1 | I65: Instalación | J65: Bogotá y alrededores | K65: Bogotá | L65: =IF(O65>0,"Despachado","En alistamiento") -> Despachado | N65: 0 | O65: N/A | P65: N/A | Q65: =IF(P65>0,"Entregado","En transito") -> Entregado | R65: 0 | S65: 0 | T65: 0 | U65: =IFERROR(IF(T65="no cumple",S65-VLOOKUP(I65,Valores!$K$1:$L$4,2,0),0),S65-VLOOKUP(K65,Valores!E:F,2,0)) -> 0
A66: 46051 | B66: enero | C66: 100279 | D66: Venta | E66: Juan Sebastian Marulanda Sanchez | F66: TECU2FNG | G66: =IFERROR(VLOOKUP(F66,Productos!$A$2:$D$277,2,0)," ") -> Electric Standing Desk GO Negro | H66: 1 | I66: =IFERROR(VLOOKUP(F66,Productos!$A$2:$D$277,3,0)," ") -> Standing Desk | J66: Caldas | K66: Manizales | L66: =IF(O66>0,"Despachado","En alistamiento") -> Despachado | M66: Coordinadora | N66: 4046556-84151501714 | O66: 46051 | P66: 46052 | Q66: =IF(P66>0,"Entregado","En transito") -> Entregado | R66: =IF(L66="Despachado",NETWORKDAYS.INTL(A66,O66,11,Valores!$A$2:$A$19)-1,"PTE") -> 0 | S66: =IF(Q66="Entregado",NETWORKDAYS.INTL(A66,P66,11,Valores!$A$2:$A$19)-1,"PTE") -> 1 | T66: =IF(Q66="Entregado",IFERROR(IF(I66=VLOOKUP(I66,Valores!$K$1:$K$4,1,0),IF(S66<=VLOOKUP(I66,Valores!$K$1:$L$4,2,0),"Cumple","No cumple")),IF(S66<=VLOOKUP(K66,Valores!E:F,2,0),"Cumple","No cumple"))) -> Cumple | U66: =IFERROR(IF(T66="no cumple",S66-VLOOKUP(I66,Valores!$K$1:$L$4,2,0),0),S66-VLOOKUP(K66,Valores!E:F,2,0)) -> 0 | W66: 35044
A67: 46051 | B67: enero | C67: 100280 | D67: Venta | E67: DIEGO ALEJANDRO DOTOR CARO | F67: TECUTCO8C | G67: =IFERROR(VLOOKUP(F67,Productos!$A$2:$D$277,2,0)," ") -> Superficie Caramelo 180x70 Clasico | H67: 1 | I67: =IFERROR(VLOOKUP(F67,Productos!$A$2:$D$277,3,0)," ") -> Superficie | J67: Bogotá y alrededores | K67: Bogotá | L67: =IF(O67>0,"Despachado","En alistamiento") -> Despachado | M67: Envía | N67: 4048927-954101383179 | O67: 46052 | P67: 46053 | Q67: =IF(P67>0,"Entregado","En transito") -> Entregado | R67: =IF(L67="Despachado",NETWORKDAYS.INTL(A67,O67,11,Valores!$A$2:$A$19)-1,"PTE") -> 1 | S67: =IF(Q67="Entregado",NETWORKDAYS.INTL(A67,P67,11,Valores!$A$2:$A$19)-1,"PTE") -> 2 | T67: =IF(Q67="Entregado",IFERROR(IF(I67=VLOOKUP(I67,Valores!$K$1:$K$4,1,0),IF(S67<=VLOOKUP(I67,Valores!$K$1:$L$4,2,0),"Cumple","No cumple")),IF(S67<=VLOOKUP(K67,Valores!E:F,2,0),"Cumple","No cumple"))) -> Cumple | U67: =IFERROR(IF(T67="no cumple",S67-VLOOKUP(I67,Valores!$K$1:$L$4,2,0),0),S67-VLOOKUP(K67,Valores!E:F,2,0)) -> 0 | W67: 32253
A68: 46051 | B68: enero | C68: 100280 | D68: Venta | E68: DIEGO ALEJANDRO DOTOR CARO | F68: TECU3FNPRO | G68: =IFERROR(VLOOKUP(F68,Productos!$A$2:$D$277,2,0)," ") -> Electric Standing Desk PRO Negro | H68: 1 | I68: =IFERROR(VLOOKUP(F68,Productos!$A$2:$D$277,3,0)," ") -> Standing Desk | J68: Bogotá y alrededores | K68: Bogotá | L68: =IF(O68>0,"Despachado","En alistamiento") -> Despachado | M68: Coordinadora | N68: 4048570-84151502337 | O68: 46052 | P68: 46055 | Q68: =IF(P68>0,"Entregado","En transito") -> Entregado | R68: =IF(L68="Despachado",NETWORKDAYS.INTL(A68,O68,11,Valores!$A$2:$A$19)-1,"PTE") -> 1 | S68: =IF(Q68="Entregado",NETWORKDAYS.INTL(A68,P68,11,Valores!$A$2:$A$19)-1,"PTE") -> 3 | T68: =IF(Q68="Entregado",IFERROR(IF(I68=VLOOKUP(I68,Valores!$K$1:$K$4,1,0),IF(S68<=VLOOKUP(I68,Valores!$K$1:$L$4,2,0),"Cumple","No cumple")),IF(S68<=VLOOKUP(K68,Valores!E:F,2,0),"Cumple","No cumple"))) -> Cumple | U68: =IFERROR(IF(T68="no cumple",S68-VLOOKUP(I68,Valores!$K$1:$L$4,2,0),0),S68-VLOOKUP(K68,Valores!E:F,2,0)) -> 0 | W68: 44550
A69: 46051 | B69: enero | C69: 100280 | D69: Venta | E69: DIEGO ALEJANDRO DOTOR CARO | F69: TECUCT | G69: =IFERROR(VLOOKUP(F69,Productos!$A$2:$D$277,2,0)," ") -> Bandeja de cables | H69: 1 | I69: =IFERROR(VLOOKUP(F69,Productos!$A$2:$D$277,3,0)," ") -> Accesorio | J69: Bogotá y alrededores | K69: Bogotá | L69: =IF(O69>0,"Despachado","En alistamiento") -> Despachado | M69: Coordinadora | N69: 4048584-84151502343 | O69: 46052 | P69: 46055 | Q69: =IF(P69>0,"Entregado","En transito") -> Entregado | R69: =IF(L69="Despachado",NETWORKDAYS.INTL(A69,O69,11,Valores!$A$2:$A$19)-1,"PTE") -> 1 | S69: =IF(Q69="Entregado",NETWORKDAYS.INTL(A69,P69,11,Valores!$A$2:$A$19)-1,"PTE") -> 3 | T69: =IF(Q69="Entregado",IFERROR(IF(I69=VLOOKUP(I69,Valores!$K$1:$K$4,1,0),IF(S69<=VLOOKUP(I69,Valores!$K$1:$L$4,2,0),"Cumple","No cumple")),IF(S69<=VLOOKUP(K69,Valores!E:F,2,0),"Cumple","No cumple"))) -> Cumple | U69: =IFERROR(IF(T69="no cumple",S69-VLOOKUP(I69,Valores!$K$1:$L$4,2,0),0),S69-VLOOKUP(K69,Valores!E:F,2,0)) -> 0 | W69: 26681
A70: 46051 | B70: enero | C70: 100280 | D70: Venta | E70: DIEGO ALEJANDRO DOTOR CARO | F70: TECURECO-80 | G70: =IFERROR(VLOOKUP(F70,Productos!$A$2:$D$277,2,0)," ") -> Repisa Escritorio Caramelo x 80cm | H70: 1 | I70: =IFERROR(VLOOKUP(F70,Productos!$A$2:$D$277,3,0)," ") -> Repisa | J70: Bogotá y alrededores | K70: Bogotá | L70: =IF(O70>0,"Despachado","En alistamiento") -> Despachado | M70: Coordinadora | N70: 4055850-84151504787 | O70: 46055 | P70: 46058 | Q70: =IF(P70>0,"Entregado","En transito") -> Entregado | R70: =IF(L70="Despachado",NETWORKDAYS.INTL(A70,O70,11,Valores!$A$2:$A$19)-1,"PTE") -> 3 | S70: =IF(Q70="Entregado",NETWORKDAYS.INTL(A70,P70,11,Valores!$A$2:$A$19)-1,"PTE") -> 6 | T70: =IF(Q70="Entregado",IFERROR(IF(I70=VLOOKUP(I70,Valores!$K$1:$K$4,1,0),IF(S70<=VLOOKUP(I70,Valores!$K$1:$L$4,2,0),"Cumple","No cumple")),IF(S70<=VLOOKUP(K70,Valores!E:F,2,0),"Cumple","No cumple"))) -> No cumple | U70: =IFERROR(IF(T70="no cumple",S70-VLOOKUP(I70,Valores!$K$1:$L$4,2,0),0),S70-VLOOKUP(K70,Valores!E:F,2,0)) -> 3 | V70: Producción | W70: 26233 | Y70: Demora en proceso de producción | Z70: Se debía pintar la bandeja de la repisa
A71: 46051 | B71: enero | C71: 100280 | D71: Venta | E71: DIEGO ALEJANDRO DOTOR CARO | G71: Servicio Instalación | H71: 1 | I71: Instalación | J71: Bogotá y alrededores | K71: Bogotá | L71: =IF(O71>0,"Despachado","En alistamiento") -> Despachado | M71: N/A | N71: N/A | O71: N/A | P71: N/A | Q71: =IF(P71>0,"Entregado","En transito") -> Entregado | R71: 0 | S71: 0 | T71: 0 | U71: =IFERROR(IF(T71="no cumple",S71-VLOOKUP(I71,Valores!$K$1:$L$4,2,0),0),S71-VLOOKUP(K71,Valores!E:F,2,0)) -> 0 | W71: 0
A72: 46052 | B72: enero | C72: 100281 | D72: Venta | E72: Luis Trigueros | F72: TECUTFE3C | G72: =IFERROR(VLOOKUP(F72,Productos!$A$2:$D$277,2,0)," ") -> Superficie Fresno Europeo 130x70 Clasico | H72: 1 | I72: =IFERROR(VLOOKUP(F72,Productos!$A$2:$D$277,3,0)," ") -> Superficie | J72: Valle del Cauca | K72: Jamundí | L72: =IF(O72>0,"Despachado","En alistamiento") -> Despachado | M72: Coordinadora | N72: 4055134-84151504450 | O72: 46055 | P72: 46056 | Q72: =IF(P72>0,"Entregado","En transito") -> Entregado | R72: =IF(L72="Despachado",NETWORKDAYS.INTL(A72,O72,11,Valores!$A$2:$A$19)-1,"PTE") -> 2 | S72: =IF(Q72="Entregado",NETWORKDAYS.INTL(A72,P72,11,Valores!$A$2:$A$19)-1,"PTE") -> 3 | T72: =IF(Q72="Entregado",IFERROR(IF(I72=VLOOKUP(I72,Valores!$K$1:$K$4,1,0),IF(S72<=VLOOKUP(I72,Valores!$K$1:$L$4,2,0),"Cumple","No cumple")),IF(S72<=VLOOKUP(K72,Valores!E:F,2,0),"Cumple","No cumple"))) -> Cumple | U72: =IFERROR(IF(T72="no cumple",S72-VLOOKUP(I72,Valores!$K$1:$L$4,2,0),0),S72-VLOOKUP(K72,Valores!E:F,2,0)) -> 0 | W72: 25952
A73: 46052 | B73: enero | C73: 100281 | D73: Venta | E73: Luis Trigueros | F73: TECUREFE -110 | G73: =IFERROR(VLOOKUP(F73,Productos!$A$2:$D$277,2,0)," ") -> Repisa Escritorio Fresno Europeo x 110cm | H73: 1 | I73: =IFERROR(VLOOKUP(F73,Productos!$A$2:$D$277,3,0)," ") -> Repisa | J73: Valle del Cauca | K73: Jamundí | L73: =IF(O73>0,"Despachado","En alistamiento") -> Despachado | M73: Coordinadora | N73: 4055134-84151504450 | O73: 46055 | P73: 46056 | Q73: =IF(P73>0,"Entregado","En transito") -> Entregado | R73: =IF(L73="Despachado",NETWORKDAYS.INTL(A73,O73,11,Valores!$A$2:$A$19)-1,"PTE") -> 2 | S73: =IF(Q73="Entregado",NETWORKDAYS.INTL(A73,P73,11,Valores!$A$2:$A$19)-1,"PTE") -> 3 | T73: =IF(Q73="Entregado",IFERROR(IF(I73=VLOOKUP(I73,Valores!$K$1:$K$4,1,0),IF(S73<=VLOOKUP(I73,Valores!$K$1:$L$4,2,0),"Cumple","No cumple")),IF(S73<=VLOOKUP(K73,Valores!E:F,2,0),"Cumple","No cumple"))) -> Cumple | U73: =IFERROR(IF(T73="no cumple",S73-VLOOKUP(I73,Valores!$K$1:$L$4,2,0),0),S73-VLOOKUP(K73,Valores!E:F,2,0)) -> 0 | W73: 0
A74: 46052 | B74: enero | C74: 100281 | D74: Venta | E74: Luis Trigueros | F74: TECU3FNPRO | G74: =IFERROR(VLOOKUP(F74,Productos!$A$2:$D$277,2,0)," ") -> Electric Standing Desk PRO Negro | H74: 1 | I74: =IFERROR(VLOOKUP(F74,Productos!$A$2:$D$277,3,0)," ") -> Standing Desk | J74: Valle del Cauca | K74: Jamundí | L74: =IF(O74>0,"Despachado","En alistamiento") -> Despachado | M74: Coordinadora | N74: 4055133-84151504449 | O74: 46055 | P74: 46056 | Q74: =IF(P74>0,"Entregado","En transito") -> Entregado | R74: =IF(L74="Despachado",NETWORKDAYS.INTL(A74,O74,11,Valores!$A$2:$A$19)-1,"PTE") -> 2 | S74: =IF(Q74="Entregado",NETWORKDAYS.INTL(A74,P74,11,Valores!$A$2:$A$19)-1,"PTE") -> 3 | T74: =IF(Q74="Entregado",IFERROR(IF(I74=VLOOKUP(I74,Valores!$K$1:$K$4,1,0),IF(S74<=VLOOKUP(I74,Valores!$K$1:$L$4,2,0),"Cumple","No cumple")),IF(S74<=VLOOKUP(K74,Valores!E:F,2,0),"Cumple","No cumple"))) -> Cumple | U74: =IFERROR(IF(T74="no cumple",S74-VLOOKUP(I74,Valores!$K$1:$L$4,2,0),0),S74-VLOOKUP(K74,Valores!E:F,2,0)) -> 0 | W74: 43114
A75: 46052 | B75: enero | C75: 100281 | D75: Venta | E75: Luis Trigueros | F75: TECUCT | G75: =IFERROR(VLOOKUP(F75,Productos!$A$2:$D$277,2,0)," ") -> Bandeja de cables | H75: 1 | I75: =IFERROR(VLOOKUP(F75,Productos!$A$2:$D$277,3,0)," ") -> Accesorio | J75: Valle del Cauca | K75: Jamundí | L75: =IF(O75>0,"Despachado","En alistamiento") -> Despachado | M75: Coordinadora | N75: 4055158-84151504463 | O75: 46055 | P75: 46056 | Q75: =IF(P75>0,"Entregado","En transito") -> Entregado | R75: =IF(L75="Despachado",NETWORKDAYS.INTL(A75,O75,11,Valores!$A$2:$A$19)-1,"PTE") -> 2 | S75: =IF(Q75="Entregado",NETWORKDAYS.INTL(A75,P75,11,Valores!$A$2:$A$19)-1,"PTE") -> 3 | T75: =IF(Q75="Entregado",IFERROR(IF(I75=VLOOKUP(I75,Valores!$K$1:$K$4,1,0),IF(S75<=VLOOKUP(I75,Valores!$K$1:$L$4,2,0),"Cumple","No cumple")),IF(S75<=VLOOKUP(K75,Valores!E:F,2,0),"Cumple","No cumple"))) -> Cumple | U75: =IFERROR(IF(T75="no cumple",S75-VLOOKUP(I75,Valores!$K$1:$L$4,2,0),0),S75-VLOOKUP(K75,Valores!E:F,2,0)) -> 0 | W75: 26681
A76: 46052 | B76: enero | C76: 100282 | D76: Venta | E76: Cristian Fernando Varela Fitzgerald | F76: TECUTCO2C-60 | G76: =IFERROR(VLOOKUP(F76,Productos!$A$2:$D$277,2,0)," ") -> Superficie Escritorio Caramelo 120x60 Clasico Small | H76: 1 | I76: =IFERROR(VLOOKUP(F76,Productos!$A$2:$D$277,3,0)," ") -> Superficie | J76: Quindío | K76: Armenia | L76: =IF(O76>0,"Despachado","En alistamiento") -> Despachado | M76: Particular | N76: N/A | O76: 46055 | P76: 46055 | Q76: =IF(P76>0,"Entregado","En transito") -> Entregado | R76: =IF(L76="Despachado",NETWORKDAYS.INTL(A76,O76,11,Valores!$A$2:$A$19)-1,"PTE") -> 2 | S76: =IF(Q76="Entregado",NETWORKDAYS.INTL(A76,P76,11,Valores!$A$2:$A$19)-1,"PTE") -> 2 | T76: =IF(Q76="Entregado",IFERROR(IF(I76=VLOOKUP(I76,Valores!$K$1:$K$4,1,0),IF(S76<=VLOOKUP(I76,Valores!$K$1:$L$4,2,0),"Cumple","No cumple")),IF(S76<=VLOOKUP(K76,Valores!E:F,2,0),"Cumple","No cumple"))) -> Cumple | U76: =IFERROR(IF(T76="no cumple",S76-VLOOKUP(I76,Valores!$K$1:$L$4,2,0),0),S76-VLOOKUP(K76,Valores!E:F,2,0)) -> 0 | W76: 40000
A77: 46052 | B77: enero | C77: 100282 | D77: Venta | E77: Cristian Fernando Varela Fitzgerald | F77: TECU2FNG | G77: =IFERROR(VLOOKUP(F77,Productos!$A$2:$D$277,2,0)," ") -> Electric Standing Desk GO Negro | H77: 1 | I77: =IFERROR(VLOOKUP(F77,Productos!$A$2:$D$277,3,0)," ") -> Standing Desk | J77: Quindío | K77: Armenia | L77: =IF(O77>0,"Despachado","En alistamiento") -> Despachado | M77: Particular | N77: N/A | O77: 46055 | P77: 46055 | Q77: =IF(P77>0,"Entregado","En transito") -> Entregado | R77: =IF(L77="Despachado",NETWORKDAYS.INTL(A77,O77,11,Valores!$A$2:$A$19)-1,"PTE") -> 2 | S77: =IF(Q77="Entregado",NETWORKDAYS.INTL(A77,P77,11,Valores!$A$2:$A$19)-1,"PTE") -> 2 | T77: =IF(Q77="Entregado",IFERROR(IF(I77=VLOOKUP(I77,Valores!$K$1:$K$4,1,0),IF(S77<=VLOOKUP(I77,Valores!$K$1:$L$4,2,0),"Cumple","No cumple")),IF(S77<=VLOOKUP(K77,Valores!E:F,2,0),"Cumple","No cumple"))) -> Cumple | U77: =IFERROR(IF(T77="no cumple",S77-VLOOKUP(I77,Valores!$K$1:$L$4,2,0),0),S77-VLOOKUP(K77,Valores!E:F,2,0)) -> 0 | W77: 0
A78: 46053 | B78: enero | C78: 100283 | D78: Venta | E78: Julio Cesar Calderón | F78: TECUTCO6C | G78: =IFERROR(VLOOKUP(F78,Productos!$A$2:$D$277,2,0)," ") -> Superficie Caramelo 160x70 Clasico | H78: 1 | I78: =IFERROR(VLOOKUP(F78,Productos!$A$2:$D$277,3,0)," ") -> Superficie | J78: Bogotá y alrededores | K78: Bogotá | L78: =IF(O78>0,"Despachado","En alistamiento") -> Despachado | M78: Envía | N78: 4059885-954101385842 | O78: 46056 | P78: 46057 | Q78: =IF(P78>0,"Entregado","En transito") -> Entregado | R78: =IF(L78="Despachado",NETWORKDAYS.INTL(A78,O78,11,Valores!$A$2:$A$19)-1,"PTE") -> 2 | S78: =IF(Q78="Entregado",NETWORKDAYS.INTL(A78,P78,11,Valores!$A$2:$A$19)-1,"PTE") -> 3 | T78: =IF(Q78="Entregado",IFERROR(IF(I78=VLOOKUP(I78,Valores!$K$1:$K$4,1,0),IF(S78<=VLOOKUP(I78,Valores!$K$1:$L$4,2,0),"Cumple","No cumple")),IF(S78<=VLOOKUP(K78,Valores!E:F,2,0),"Cumple","No cumple"))) -> Cumple | U78: =IFERROR(IF(T78="no cumple",S78-VLOOKUP(I78,Valores!$K$1:$L$4,2,0),0),S78-VLOOKUP(K78,Valores!E:F,2,0)) -> 0 | W78: 32253
A79: 46053 | B79: enero | C79: 100283 | D79: Venta | E79: Julio Cesar Calderón | F79: TECU3FNCRO | G79: =IFERROR(VLOOKUP(F79,Productos!$A$2:$D$277,2,0)," ") -> Electric Standing Desk PRO Negro circular | H79: 1 | I79: =IFERROR(VLOOKUP(F79,Productos!$A$2:$D$277,3,0)," ") -> Standing Desk | J79: Bogotá y alrededores | K79: Bogotá | L79: =IF(O79>0,"Despachado","En alistamiento") -> Despachado | M79: Coordinadora | N79: 4059912-84151506167 | O79: 46056 | P79: 46058 | Q79: =IF(P79>0,"Entregado","En transito") -> Entregado | R79: =IF(L79="Despachado",NETWORKDAYS.INTL(A79,O79,11,Valores!$A$2:$A$19)-1,"PTE") -> 2 | S79: =IF(Q79="Entregado",NETWORKDAYS.INTL(A79,P79,11,Valores!$A$2:$A$19)-1,"PTE") -> 4 | T79: =IF(Q79="Entregado",IFERROR(IF(I79=VLOOKUP(I79,Valores!$K$1:$K$4,1,0),IF(S79<=VLOOKUP(I79,Valores!$K$1:$L$4,2,0),"Cumple","No cumple")),IF(S79<=VLOOKUP(K79,Valores!E:F,2,0),"Cumple","No cumple"))) -> No cumple | U79: =IFERROR(IF(T79="no cumple",S79-VLOOKUP(I79,Valores!$K$1:$L$4,2,0),0),S79-VLOOKUP(K79,Valores!E:F,2,0)) -> 1 | V79: Producción - Transporte | W79: 44550 | Y79: Demora en entrega
A80: 46053 | B80: enero | C80: 100284 | D80: Venta | E80: Julio Cesar Calderón | F80: TECUCT | G80: =IFERROR(VLOOKUP(F80,Productos!$A$2:$D$277,2,0)," ") -> Bandeja de cables | H80: 1 | I80: =IFERROR(VLOOKUP(F80,Productos!$A$2:$D$277,3,0)," ") -> Accesorio | J80: Bogotá y alrededores | K80: Bogotá | L80: =IF(O80>0,"Despachado","En alistamiento") -> Despachado | M80: Coordinadora | N80: 4059942-84151506184 | O80: 46056 | P80: 46058 | Q80: =IF(P80>0,"Entregado","En transito") -> Entregado | R80: =IF(L80="Despachado",NETWORKDAYS.INTL(A80,O80,11,Valores!$A$2:$A$19)-1,"PTE") -> 2 | S80: =IF(Q80="Entregado",NETWORKDAYS.INTL(A80,P80,11,Valores!$A$2:$A$19)-1,"PTE") -> 4 | T80: =IF(Q80="Entregado",IFERROR(IF(I80=VLOOKUP(I80,Valores!$K$1:$K$4,1,0),IF(S80<=VLOOKUP(I80,Valores!$K$1:$L$4,2,0),"Cumple","No cumple")),IF(S80<=VLOOKUP(K80,Valores!E:F,2,0),"Cumple","No cumple"))) -> No cumple | U80: =IFERROR(IF(T80="no cumple",S80-VLOOKUP(I80,Valores!$K$1:$L$4,2,0),0),S80-VLOOKUP(K80,Valores!E:F,2,0)) -> 1 | V80: Producción - Transporte | W80: 26681 | Y80: Demora en entrega
A81: 46055 | B81: febrero | C81: 100285 | D81: Venta | E81: Julian David Gomez Perilla | F81: TECUTCO6M | G81: =IFERROR(VLOOKUP(F81,Productos!$A$2:$D$277,2,0)," ") -> Superficie Caramelo 160x70 Moderno | H81: 1 | I81: =IFERROR(VLOOKUP(F81,Productos!$A$2:$D$277,3,0)," ") -> Superficie | J81: Bogotá y alrededores | K81: Bogotá | L81: =IF(O81>0,"Despachado","En alistamiento") -> Despachado | M81: Envía | N81: 4059930-954101385844 | O81: 46056 | P81: 46057 | Q81: =IF(P81>0,"Entregado","En transito") -> Entregado | R81: =IF(L81="Despachado",NETWORKDAYS.INTL(A81,O81,11,Valores!$A$2:$A$19)-1,"PTE") -> 1 | S81: =IF(Q81="Entregado",NETWORKDAYS.INTL(A81,P81,11,Valores!$A$2:$A$19)-1,"PTE") -> 2 | T81: =IF(Q81="Entregado",IFERROR(IF(I81=VLOOKUP(I81,Valores!$K$1:$K$4,1,0),IF(S81<=VLOOKUP(I81,Valores!$K$1:$L$4,2,0),"Cumple","No cumple")),IF(S81<=VLOOKUP(K81,Valores!E:F,2,0),"Cumple","No cumple"))) -> Cumple | U81: =IFERROR(IF(T81="no cumple",S81-VLOOKUP(I81,Valores!$K$1:$L$4,2,0),0),S81-VLOOKUP(K81,Valores!E:F,2,0)) -> 0 | W81: 32253
A82: 46055 | B82: febrero | C82: 100285 | D82: Venta | E82: Julian David Gomez Perilla | F82: TECU3FNPRO | G82: =IFERROR(VLOOKUP(F82,Productos!$A$2:$D$277,2,0)," ") -> Electric Standing Desk PRO Negro | H82: 1 | I82: =IFERROR(VLOOKUP(F82,Productos!$A$2:$D$277,3,0)," ") -> Standing Desk | J82: Bogotá y alrededores | K82: Bogotá | L82: =IF(O82>0,"Despachado","En alistamiento") -> Despachado | M82: Coordinadora | N82: 4059984-84151506204 | O82: 46056 | P82: 46058 | Q82: =IF(P82>0,"Entregado","En transito") -> Entregado | R82: =IF(L82="Despachado",NETWORKDAYS.INTL(A82,O82,11,Valores!$A$2:$A$19)-1,"PTE") -> 1 | S82: =IF(Q82="Entregado",NETWORKDAYS.INTL(A82,P82,11,Valores!$A$2:$A$19)-1,"PTE") -> 3 | T82: =IF(Q82="Entregado",IFERROR(IF(I82=VLOOKUP(I82,Valores!$K$1:$K$4,1,0),IF(S82<=VLOOKUP(I82,Valores!$K$1:$L$4,2,0),"Cumple","No cumple")),IF(S82<=VLOOKUP(K82,Valores!E:F,2,0),"Cumple","No cumple"))) -> Cumple | U82: =IFERROR(IF(T82="no cumple",S82-VLOOKUP(I82,Valores!$K$1:$L$4,2,0),0),S82-VLOOKUP(K82,Valores!E:F,2,0)) -> 0 | W82: 44550
A83: 46055 | B83: febrero | C83: 100286 | D83: Venta | E83: Javier Villa | F83: TECUBLS | G83: =IFERROR(VLOOKUP(F83,Productos!$A$2:$D$277,2,0)," ") -> Laptop Stand B | H83: 1 | I83: =IFERROR(VLOOKUP(F83,Productos!$A$2:$D$277,3,0)," ") -> Accesorio | J83: Bogotá y alrededores | K83: Bogotá | L83: =IF(O83>0,"Despachado","En alistamiento") -> Despachado | M83: Coordinadora | N83: 4059994-84151506206 | O83: 46056 | P83: 46058 | Q83: =IF(P83>0,"Entregado","En transito") -> Entregado | R83: =IF(L83="Despachado",NETWORKDAYS.INTL(A83,O83,11,Valores!$A$2:$A$19)-1,"PTE") -> 1 | S83: =IF(Q83="Entregado",NETWORKDAYS.INTL(A83,P83,11,Valores!$A$2:$A$19)-1,"PTE") -> 3 | T83: =IF(Q83="Entregado",IFERROR(IF(I83=VLOOKUP(I83,Valores!$K$1:$K$4,1,0),IF(S83<=VLOOKUP(I83,Valores!$K$1:$L$4,2,0),"Cumple","No cumple")),IF(S83<=VLOOKUP(K83,Valores!E:F,2,0),"Cumple","No cumple"))) -> Cumple | U83: =IFERROR(IF(T83="no cumple",S83-VLOOKUP(I83,Valores!$K$1:$L$4,2,0),0),S83-VLOOKUP(K83,Valores!E:F,2,0)) -> 0 | W83: 26681
A84: 46056 | B84: febrero | C84: 100287 | D84: Venta | E84: Harold Muñoz | F84: TECUREFE -80 | G84: =IFERROR(VLOOKUP(F84,Productos!$A$2:$D$277,2,0)," ") -> Repisa Escritorio Fresno Europeo x 80cm | H84: 1 | I84: =IFERROR(VLOOKUP(F84,Productos!$A$2:$D$277,3,0)," ") -> Repisa | J84: Bogotá y alrededores | K84: Bogotá | L84: =IF(O84>0,"Despachado","En alistamiento") -> Despachado | M84: Coordinadora | N84: 4070707-84151509913 | O84: 46059 | P84: 46060 | Q84: =IF(P84>0,"Entregado","En transito") -> Entregado | R84: =IF(L84="Despachado",NETWORKDAYS.INTL(A84,O84,11,Valores!$A$2:$A$19)-1,"PTE") -> 3 | S84: =IF(Q84="Entregado",NETWORKDAYS.INTL(A84,P84,11,Valores!$A$2:$A$19)-1,"PTE") -> 4 | T84: =IF(Q84="Entregado",IFERROR(IF(I84=VLOOKUP(I84,Valores!$K$1:$K$4,1,0),IF(S84<=VLOOKUP(I84,Valores!$K$1:$L$4,2,0),"Cumple","No cumple")),IF(S84<=VLOOKUP(K84,Valores!E:F,2,0),"Cumple","No cumple"))) -> No cumple | U84: =IFERROR(IF(T84="no cumple",S84-VLOOKUP(I84,Valores!$K$1:$L$4,2,0),0),S84-VLOOKUP(K84,Valores!E:F,2,0)) -> 1 | V84: Producción | W84: 25233 | Y84: Demora en proceso de producción | Z84: No habían bandejas de la repisa
A85: 46059 | B85: febrero | C85: 100288 | D85: Venta | E85: Laura Del Sol Garcia Ruiz | F85: TECU2CBC-65 | G85: =IFERROR(VLOOKUP(F85,Productos!$A$2:$D$277,2,0)," ") -> Cajonero 2.0 Bicolor Caramelo x65cm | H85: 1 | I85: =IFERROR(VLOOKUP(F85,Productos!$A$2:$D$277,3,0)," ") -> Archivador | J85: Quindío | K85: Armenia | L85: =IF(O85>0,"Despachado","En alistamiento") -> Despachado | M85: Particular | N85: N/A | O85: 46063 | P85: 46063 | Q85: =IF(P85>0,"Entregado","En transito") -> Entregado | R85: =IF(L85="Despachado",NETWORKDAYS.INTL(A85,O85,11,Valores!$A$2:$A$19)-1,"PTE") -> 3 | S85: =IF(Q85="Entregado",NETWORKDAYS.INTL(A85,P85,11,Valores!$A$2:$A$19)-1,"PTE") -> 3 | T85: =IF(Q85="Entregado",IFERROR(IF(I85=VLOOKUP(I85,Valores!$K$1:$K$4,1,0),IF(S85<=VLOOKUP(I85,Valores!$K$1:$L$4,2,0),"Cumple","No cumple")),IF(S85<=VLOOKUP(K85,Valores!E:F,2,0),"Cumple","No cumple"))) -> Cumple | U85: =IFERROR(IF(T85="no cumple",S85-VLOOKUP(I85,Valores!$K$1:$L$4,2,0),0),S85-VLOOKUP(K85,Valores!E:F,2,0)) -> 0 | W85: 50000
A86: 46059 | B86: febrero | C86: 100288 | D86: Venta | E86: Laura Del Sol Garcia Ruiz | F86: TECU2CBC-65 | G86: =IFERROR(VLOOKUP(F86,Productos!$A$2:$D$277,2,0)," ") -> Cajonero 2.0 Bicolor Caramelo x65cm | H86: 1 | I86: =IFERROR(VLOOKUP(F86,Productos!$A$2:$D$277,3,0)," ") -> Archivador | J86: Quindío | K86: Armenia | L86: =IF(O86>0,"Despachado","En alistamiento") -> Despachado | M86: Particular | N86: N/A | O86: 46063 | P86: 46063 | Q86: =IF(P86>0,"Entregado","En transito") -> Entregado | R86: =IF(L86="Despachado",NETWORKDAYS.INTL(A86,O86,11,Valores!$A$2:$A$19)-1,"PTE") -> 3 | S86: =IF(Q86="Entregado",NETWORKDAYS.INTL(A86,P86,11,Valores!$A$2:$A$19)-1,"PTE") -> 3 | T86: =IF(Q86="Entregado",IFERROR(IF(I86=VLOOKUP(I86,Valores!$K$1:$K$4,1,0),IF(S86<=VLOOKUP(I86,Valores!$K$1:$L$4,2,0),"Cumple","No cumple")),IF(S86<=VLOOKUP(K86,Valores!E:F,2,0),"Cumple","No cumple"))) -> Cumple | U86: =IFERROR(IF(T86="no cumple",S86-VLOOKUP(I86,Valores!$K$1:$L$4,2,0),0),S86-VLOOKUP(K86,Valores!E:F,2,0)) -> 0 | W86: 0
A87: 46061 | B87: febrero | C87: 100289 | D87: Venta | E87: Brayan Camilo Clavijo Gomez | F87: TECUTRN8C-80 | G87: =IFERROR(VLOOKUP(F87,Productos!$A$2:$D$277,2,0)," ") -> Superficie Escritorio Roble Negro 180x80 Clasico | H87: 1 | I87: =IFERROR(VLOOKUP(F87,Productos!$A$2:$D$277,3,0)," ") -> Superficie | J87: Meta | K87: Villavicencio | L87: =IF(O87>0,"Despachado","En alistamiento") -> Despachado | M87: Envía | N87: 4080860-954101391564 | O87: 46063 | P87: 46065 | Q87: =IF(P87>0,"Entregado","En transito") -> Entregado | R87: =IF(L87="Despachado",NETWORKDAYS.INTL(A87,O87,11,Valores!$A$2:$A$19)-1,"PTE") -> 1 | S87: =IF(Q87="Entregado",NETWORKDAYS.INTL(A87,P87,11,Valores!$A$2:$A$19)-1,"PTE") -> 3 | T87: =IF(Q87="Entregado",IFERROR(IF(I87=VLOOKUP(I87,Valores!$K$1:$K$4,1,0),IF(S87<=VLOOKUP(I87,Valores!$K$1:$L$4,2,0),"Cumple","No cumple")),IF(S87<=VLOOKUP(K87,Valores!E:F,2,0),"Cumple","No cumple"))) -> Cumple | U87: =IFERROR(IF(T87="no cumple",S87-VLOOKUP(I87,Valores!$K$1:$L$4,2,0),0),S87-VLOOKUP(K87,Valores!E:F,2,0)) -> 0 | W87: 63431
A88: 46061 | B88: febrero | C88: 100289 | D88: Venta | E88: Brayan Camilo Clavijo Gomez | F88: TECU3FNCRO | G88: =IFERROR(VLOOKUP(F88,Productos!$A$2:$D$277,2,0)," ") -> Electric Standing Desk PRO Negro circular | H88: 1 | I88: =IFERROR(VLOOKUP(F88,Productos!$A$2:$D$277,3,0)," ") -> Standing Desk | J88: Meta | K88: Villavicencio | L88: =IF(O88>0,"Despachado","En alistamiento") -> Despachado | M88: Coordinadora | N88: 4080266-84151513163 | O88: 46063 | P88: 46065 | Q88: =IF(P88>0,"Entregado","En transito") -> Entregado | R88: =IF(L88="Despachado",NETWORKDAYS.INTL(A88,O88,11,Valores!$A$2:$A$19)-1,"PTE") -> 1 | S88: =IF(Q88="Entregado",NETWORKDAYS.INTL(A88,P88,11,Valores!$A$2:$A$19)-1,"PTE") -> 3 | T88: =IF(Q88="Entregado",IFERROR(IF(I88=VLOOKUP(I88,Valores!$K$1:$K$4,1,0),IF(S88<=VLOOKUP(I88,Valores!$K$1:$L$4,2,0),"Cumple","No cumple")),IF(S88<=VLOOKUP(K88,Valores!E:F,2,0),"Cumple","No cumple"))) -> Cumple | U88: =IFERROR(IF(T88="no cumple",S88-VLOOKUP(I88,Valores!$K$1:$L$4,2,0),0),S88-VLOOKUP(K88,Valores!E:F,2,0)) -> 0 | W88: 65599
A89: 46063 | B89: febrero | C89: 100290 | D89: Venta | E89: Ricardo Alfonso Escobar Rojas | F89: TECUTCO2C-60 | G89: =IFERROR(VLOOKUP(F89,Productos!$A$2:$D$277,2,0)," ") -> Superficie Escritorio Caramelo 120x60 Clasico Small | H89: 1 | I89: =IFERROR(VLOOKUP(F89,Productos!$A$2:$D$277,3,0)," ") -> Superficie | J89: Bogotá y alrededores | K89: Bogotá | L89: =IF(O89>0,"Despachado","En alistamiento") -> Despachado | M89: Coordinadora | N89: 4084066-84151514430 | O89: 46064 | P89: 46067 | Q89: =IF(P89>0,"Entregado","En transito") -> Entregado | R89: =IF(L89="Despachado",NETWORKDAYS.INTL(A89,O89,11,Valores!$A$2:$A$19)-1,"PTE") -> 1 | S89: =IF(Q89="Entregado",NETWORKDAYS.INTL(A89,P89,11,Valores!$A$2:$A$19)-1,"PTE") -> 4 | T89: =IF(Q89="Entregado",IFERROR(IF(I89=VLOOKUP(I89,Valores!$K$1:$K$4,1,0),IF(S89<=VLOOKUP(I89,Valores!$K$1:$L$4,2,0),"Cumple","No cumple")),IF(S89<=VLOOKUP(K89,Valores!E:F,2,0),"Cumple","No cumple"))) -> No cumple | U89: =IFERROR(IF(T89="no cumple",S89-VLOOKUP(I89,Valores!$K$1:$L$4,2,0),0),S89-VLOOKUP(K89,Valores!E:F,2,0)) -> 1 | V89: Transporte | W89: 25952 | Y89: Demora en entrega
A90: 46063 | B90: febrero | C90: 100290 | D90: Venta | E90: Ricardo Alfonso Escobar Rojas | F90: TECU2FNG | G90: =IFERROR(VLOOKUP(F90,Productos!$A$2:$D$277,2,0)," ") -> Electric Standing Desk GO Negro | H90: 1 | I90: =IFERROR(VLOOKUP(F90,Productos!$A$2:$D$277,3,0)," ") -> Standing Desk | J90: Bogotá y alrededores | K90: Bogotá | L90: =IF(O90>0,"Despachado","En alistamiento") -> Despachado | M90: Coordinadora | N90: 4084065-84151514429 | O90: 46064 | P90: 46065 | Q90: =IF(P90>0,"Entregado","En transito") -> Entregado | R90: =IF(L90="Despachado",NETWORKDAYS.INTL(A90,O90,11,Valores!$A$2:$A$19)-1,"PTE") -> 1 | S90: =IF(Q90="Entregado",NETWORKDAYS.INTL(A90,P90,11,Valores!$A$2:$A$19)-1,"PTE") -> 2 | T90: =IF(Q90="Entregado",IFERROR(IF(I90=VLOOKUP(I90,Valores!$K$1:$K$4,1,0),IF(S90<=VLOOKUP(I90,Valores!$K$1:$L$4,2,0),"Cumple","No cumple")),IF(S90<=VLOOKUP(K90,Valores!E:F,2,0),"Cumple","No cumple"))) -> Cumple | U90: =IFERROR(IF(T90="no cumple",S90-VLOOKUP(I90,Valores!$K$1:$L$4,2,0),0),S90-VLOOKUP(K90,Valores!E:F,2,0)) -> 0 | W90: 43114
A91: 46063 | B91: febrero | C91: 100291 | D91: Venta | E91: Luis Camacho | F91: TECUTCO2C | G91: =IFERROR(VLOOKUP(F91,Productos!$A$2:$D$277,2,0)," ") -> Superficie Caramelo 120x70 Clasico Small | H91: 1 | I91: =IFERROR(VLOOKUP(F91,Productos!$A$2:$D$277,3,0)," ") -> Superficie | J91: Bogotá y alrededores | K91: Bogotá | L91: =IF(O91>0,"Despachado","En alistamiento") -> Despachado | M91: Coordinadora | N91: 4084092-84151514438 | O91: 46064 | P91: 46065 | Q91: =IF(P91>0,"Entregado","En transito") -> Entregado | R91: =IF(L91="Despachado",NETWORKDAYS.INTL(A91,O91,11,Valores!$A$2:$A$19)-1,"PTE") -> 1 | S91: =IF(Q91="Entregado",NETWORKDAYS.INTL(A91,P91,11,Valores!$A$2:$A$19)-1,"PTE") -> 2 | T91: =IF(Q91="Entregado",IFERROR(IF(I91=VLOOKUP(I91,Valores!$K$1:$K$4,1,0),IF(S91<=VLOOKUP(I91,Valores!$K$1:$L$4,2,0),"Cumple","No cumple")),IF(S91<=VLOOKUP(K91,Valores!E:F,2,0),"Cumple","No cumple"))) -> Cumple | U91: =IFERROR(IF(T91="no cumple",S91-VLOOKUP(I91,Valores!$K$1:$L$4,2,0),0),S91-VLOOKUP(K91,Valores!E:F,2,0)) -> 0 | W91: 25952
A92: 46063 | B92: febrero | C92: 100291 | D92: Venta | E92: Luis Camacho | F92: TECU2FNG | G92: =IFERROR(VLOOKUP(F92,Productos!$A$2:$D$277,2,0)," ") -> Electric Standing Desk GO Negro | H92: 1 | I92: =IFERROR(VLOOKUP(F92,Productos!$A$2:$D$277,3,0)," ") -> Standing Desk | J92: Bogotá y alrededores | K92: Bogotá | L92: =IF(O92>0,"Despachado","En alistamiento") -> Despachado | M92: Coordinadora | N92: 4084091-84151514437 | O92: 46064 | P92: 46065 | Q92: =IF(P92>0,"Entregado","En transito") -> Entregado | R92: =IF(L92="Despachado",NETWORKDAYS.INTL(A92,O92,11,Valores!$A$2:$A$19)-1,"PTE") -> 1 | S92: =IF(Q92="Entregado",NETWORKDAYS.INTL(A92,P92,11,Valores!$A$2:$A$19)-1,"PTE") -> 2 | T92: =IF(Q92="Entregado",IFERROR(IF(I92=VLOOKUP(I92,Valores!$K$1:$K$4,1,0),IF(S92<=VLOOKUP(I92,Valores!$K$1:$L$4,2,0),"Cumple","No cumple")),IF(S92<=VLOOKUP(K92,Valores!E:F,2,0),"Cumple","No cumple"))) -> Cumple | U92: =IFERROR(IF(T92="no cumple",S92-VLOOKUP(I92,Valores!$K$1:$L$4,2,0),0),S92-VLOOKUP(K92,Valores!E:F,2,0)) -> 0 | W92: 43114
A93: 46063 | B93: febrero | C93: 100292 | D93: Venta | E93: Andres Sampedro | F93: TECUCT | G93: =IFERROR(VLOOKUP(F93,Productos!$A$2:$D$277,2,0)," ") -> Bandeja de cables | H93: 1 | I93: =IFERROR(VLOOKUP(F93,Productos!$A$2:$D$277,3,0)," ") -> Accesorio | J93: Bogotá y alrededores | K93: Bogotá | L93: =IF(O93>0,"Despachado","En alistamiento") -> Despachado | M93: Coordinadora | N93: 4085232-84151514843 | O93: 46064 | P93: 46065 | Q93: =IF(P93>0,"Entregado","En transito") -> Entregado | R93: =IF(L93="Despachado",NETWORKDAYS.INTL(A93,O93,11,Valores!$A$2:$A$19)-1,"PTE") -> 1 | S93: =IF(Q93="Entregado",NETWORKDAYS.INTL(A93,P93,11,Valores!$A$2:$A$19)-1,"PTE") -> 2 | T93: =IF(Q93="Entregado",IFERROR(IF(I93=VLOOKUP(I93,Valores!$K$1:$K$4,1,0),IF(S93<=VLOOKUP(I93,Valores!$K$1:$L$4,2,0),"Cumple","No cumple")),IF(S93<=VLOOKUP(K93,Valores!E:F,2,0),"Cumple","No cumple"))) -> Cumple | U93: =IFERROR(IF(T93="no cumple",S93-VLOOKUP(I93,Valores!$K$1:$L$4,2,0),0),S93-VLOOKUP(K93,Valores!E:F,2,0)) -> 0 | W93: 26681
A94: 46065 | B94: febrero | C94: 100293 | D94: Venta | E94: Carlos Andres Carrero Saldarriaga | F94: TECUTRN20C-80 | G94: =IFERROR(VLOOKUP(F94,Productos!$A$2:$D$277,2,0)," ") -> Superficie Escritorio Roble Negro 200x80 Clasico | H94: 1 | I94: =IFERROR(VLOOKUP(F94,Productos!$A$2:$D$277,3,0)," ") -> Superficie | J94: Antioquia | K94: Medellín | L94: =IF(O94>0,"Despachado","En alistamiento") -> Despachado | M94: Envía | N94: 4087332-954101393148 | O94: 46065 | P94: 46066 | Q94: =IF(P94>0,"Entregado","En transito") -> Entregado | R94: =IF(L94="Despachado",NETWORKDAYS.INTL(A94,O94,11,Valores!$A$2:$A$19)-1,"PTE") -> 0 | S94: =IF(Q94="Entregado",NETWORKDAYS.INTL(A94,P94,11,Valores!$A$2:$A$19)-1,"PTE") -> 1 | T94: =IF(Q94="Entregado",IFERROR(IF(I94=VLOOKUP(I94,Valores!$K$1:$K$4,1,0),IF(S94<=VLOOKUP(I94,Valores!$K$1:$L$4,2,0),"Cumple","No cumple")),IF(S94<=VLOOKUP(K94,Valores!E:F,2,0),"Cumple","No cumple"))) -> Cumple | U94: =IFERROR(IF(T94="no cumple",S94-VLOOKUP(I94,Valores!$K$1:$L$4,2,0),0),S94-VLOOKUP(K94,Valores!E:F,2,0)) -> 0 | W94: 45071
A95: 46065 | B95: febrero | C95: 100293 | D95: Venta | E95: Carlos Andres Carrero Saldarriaga | F95: TECU3FNPRO | G95: =IFERROR(VLOOKUP(F95,Productos!$A$2:$D$277,2,0)," ") -> Electric Standing Desk PRO Negro | H95: 1 | I95: =IFERROR(VLOOKUP(F95,Productos!$A$2:$D$277,3,0)," ") -> Standing Desk | J95: Antioquia | K95: Medellín | L95: =IF(O95>0,"Despachado","En alistamiento") -> Despachado | M95: Coordinadora | N95: 4087324-84151515548 | O95: 46065 | P95: 46066 | Q95: =IF(P95>0,"Entregado","En transito") -> Entregado | R95: =IF(L95="Despachado",NETWORKDAYS.INTL(A95,O95,11,Valores!$A$2:$A$19)-1,"PTE") -> 0 | S95: =IF(Q95="Entregado",NETWORKDAYS.INTL(A95,P95,11,Valores!$A$2:$A$19)-1,"PTE") -> 1 | T95: =IF(Q95="Entregado",IFERROR(IF(I95=VLOOKUP(I95,Valores!$K$1:$K$4,1,0),IF(S95<=VLOOKUP(I95,Valores!$K$1:$L$4,2,0),"Cumple","No cumple")),IF(S95<=VLOOKUP(K95,Valores!E:F,2,0),"Cumple","No cumple"))) -> Cumple | U95: =IFERROR(IF(T95="no cumple",S95-VLOOKUP(I95,Valores!$K$1:$L$4,2,0),0),S95-VLOOKUP(K95,Valores!E:F,2,0)) -> 0 | W95: 44550
A96: 46065 | B96: febrero | C96: 100293 | D96: Venta | E96: Carlos Andres Carrero Saldarriaga | G96: Servicio Instalación | H96: 1 | I96: Instalación | J96: Antioquia | K96: Medellín | L96: =IF(O96>0,"Despachado","En alistamiento") -> Despachado | M96: N/A | N96: N/A | O96: N/A | P96: N/A | Q96: =IF(P96>0,"Entregado","En transito") -> Entregado | R96: 0 | S96: 0 | T96: 0 | U96: =IFERROR(IF(T96="no cumple",S96-VLOOKUP(I96,Valores!$K$1:$L$4,2,0),0),S96-VLOOKUP(K96,Valores!E:F,2,0)) -> 0 | W96: 0
A97: 46065 | B97: febrero | C97: 100294 | D97: Venta | E97: Camilo Fernandez | F97: TECUAFE | G97: =IFERROR(VLOOKUP(F97,Productos!$A$2:$D$277,2,0)," ") -> Archivador TECU Fresno Europeo | H97: 1 | I97: =IFERROR(VLOOKUP(F97,Productos!$A$2:$D$277,3,0)," ") -> Archivador | J97: Bogotá y alrededores | K97: Bogotá | L97: =IF(O97>0,"Despachado","En alistamiento") -> Despachado | M97: Envía | N97: 4090685-954101394045 | O97: 46066 | P97: 46067 | Q97: =IF(P97>0,"Entregado","En transito") -> Entregado | R97: =IF(L97="Despachado",NETWORKDAYS.INTL(A97,O97,11,Valores!$A$2:$A$19)-1,"PTE") -> 1 | S97: =IF(Q97="Entregado",NETWORKDAYS.INTL(A97,P97,11,Valores!$A$2:$A$19)-1,"PTE") -> 2 | T97: =IF(Q97="Entregado",IFERROR(IF(I97=VLOOKUP(I97,Valores!$K$1:$K$4,1,0),IF(S97<=VLOOKUP(I97,Valores!$K$1:$L$4,2,0),"Cumple","No cumple")),IF(S97<=VLOOKUP(K97,Valores!E:F,2,0),"Cumple","No cumple"))) -> Cumple | U97: =IFERROR(IF(T97="no cumple",S97-VLOOKUP(I97,Valores!$K$1:$L$4,2,0),0),S97-VLOOKUP(K97,Valores!E:F,2,0)) -> 0 | W97: 57135
A98: 46065 | B98: febrero | C98: 100295 | D98: Venta | E98: Jonathan Montes | F98: TECUBDPA | G98: =IFERROR(VLOOKUP(F98,Productos!$A$2:$D$277,2,0)," ") -> Desk Pad B Negro Azul | H98: 1 | I98: =IFERROR(VLOOKUP(F98,Productos!$A$2:$D$277,3,0)," ") -> Accesorio | J98: Antioquia | K98: La ceja | L98: =IF(O98>0,"Despachado","En alistamiento") -> Despachado | M98: Coordinadora | N98: 4088436-84151515959 | O98: 46065 | P98: 46067 | Q98: =IF(P98>0,"Entregado","En transito") -> Entregado | R98: =IF(L98="Despachado",NETWORKDAYS.INTL(A98,O98,11,Valores!$A$2:$A$19)-1,"PTE") -> 0 | S98: =IF(Q98="Entregado",NETWORKDAYS.INTL(A98,P98,11,Valores!$A$2:$A$19)-1,"PTE") -> 2 | T98: =IF(Q98="Entregado",IFERROR(IF(I98=VLOOKUP(I98,Valores!$K$1:$K$4,1,0),IF(S98<=VLOOKUP(I98,Valores!$K$1:$L$4,2,0),"Cumple","No cumple")),IF(S98<=VLOOKUP(K98,Valores!E:F,2,0),"Cumple","No cumple"))) -> Cumple | U98: =IFERROR(IF(T98="no cumple",S98-VLOOKUP(I98,Valores!$K$1:$L$4,2,0),0),S98-VLOOKUP(K98,Valores!E:F,2,0)) -> 0 | W98: 17787
A99: 46066 | B99: febrero | C99: 100296 | D99: Venta | E99: Daniel Restrepo | F99: TECUTFE4C-60 | G99: =IFERROR(VLOOKUP(F99,Productos!$A$2:$D$277,2,0)," ") -> Superficie Escritorio Fresno Europeo 140x60 Clasico | H99: 1 | I99: =IFERROR(VLOOKUP(F99,Productos!$A$2:$D$277,3,0)," ") -> Superficie | J99: Antioquia | K99: Sabaneta | L99: =IF(O99>0,"Despachado","En alistamiento") -> Despachado | M99: Coordinadora | N99: 4096674-84151518709 | O99: 46069 | P99: 46070 | Q99: =IF(P99>0,"Entregado","En transito") -> Entregado | R99: =IF(L99="Despachado",NETWORKDAYS.INTL(A99,O99,11,Valores!$A$2:$A$19)-1,"PTE") -> 2 | S99: =IF(Q99="Entregado",NETWORKDAYS.INTL(A99,P99,11,Valores!$A$2:$A$19)-1,"PTE") -> 3 | T99: =IF(Q99="Entregado",IFERROR(IF(I99=VLOOKUP(I99,Valores!$K$1:$K$4,1,0),IF(S99<=VLOOKUP(I99,Valores!$K$1:$L$4,2,0),"Cumple","No cumple")),IF(S99<=VLOOKUP(K99,Valores!E:F,2,0),"Cumple","No cumple"))) -> Cumple | U99: =IFERROR(IF(T99="no cumple",S99-VLOOKUP(I99,Valores!$K$1:$L$4,2,0),0),S99-VLOOKUP(K99,Valores!E:F,2,0)) -> 0 | W99: 25952
A100: 46066 | B100: febrero | C100: 100296 | D100: Venta | E100: Daniel Restrepo | F100: TECU2FNG | G100: =IFERROR(VLOOKUP(F100,Productos!$A$2:$D$277,2,0)," ") -> Electric Standing Desk GO Negro | H100: 1 | I100: =IFERROR(VLOOKUP(F100,Productos!$A$2:$D$277,3,0)," ") -> Standing Desk | J100: Antioquia | K100: Sabaneta | L100: =IF(O100>0,"Despachado","En alistamiento") -> Despachado | M100: Coordinadora | N100: 4096670-84151518706 | O100: 46069 | P100: 46070 | Q100: =IF(P100>0,"Entregado","En transito") -> Entregado | R100: =IF(L100="Despachado",NETWORKDAYS.INTL(A100,O100,11,Valores!$A$2:$A$19)-1,"PTE") -> 2 | S100: =IF(Q100="Entregado",NETWORKDAYS.INTL(A100,P100,11,Valores!$A$2:$A$19)-1,"PTE") -> 3 | T100: =IF(Q100="Entregado",IFERROR(IF(I100=VLOOKUP(I100,Valores!$K$1:$K$4,1,0),IF(S100<=VLOOKUP(I100,Valores!$K$1:$L$4,2,0),"Cumple","No cumple")),IF(S100<=VLOOKUP(K100,Valores!E:F,2,0),"Cumple","No cumple"))) -> Cumple | U100: =IFERROR(IF(T100="no cumple",S100-VLOOKUP(I100,Valores!$K$1:$L$4,2,0),0),S100-VLOOKUP(K100,Valores!E:F,2,0)) -> 0 | W100: 43114
A101: 46066 | B101: febrero | C101: 100297 | D101: Venta | E101: SQDM SAS / NELSON MOLINA | F101: TECUTRM8C | G101: =IFERROR(VLOOKUP(F101,Productos!$A$2:$D$277,2,0)," ") -> Superficie Roble Miel 180x75 Clasico | H101: 1 | I101: =IFERROR(VLOOKUP(F101,Productos!$A$2:$D$277,3,0)," ") -> Superficie | J101: Bogotá y alrededores | K101: Bogotá | L101: =IF(O101>0,"Despachado","En alistamiento") -> Despachado | M101: Envía | N101: 4122482-954101401758 | O101: 46077 | P101: 46078 | Q101: =IF(P101>0,"Entregado","En transito") -> Entregado | R101: =IF(L101="Despachado",NETWORKDAYS.INTL(A101,O101,11,Valores!$A$2:$A$19)-1,"PTE") -> 9 | S101: =IF(Q101="Entregado",NETWORKDAYS.INTL(A101,P101,11,Valores!$A$2:$A$19)-1,"PTE") -> 10 | T101: =IF(Q101="Entregado",IFERROR(IF(I101=VLOOKUP(I101,Valores!$K$1:$K$4,1,0),IF(S101<=VLOOKUP(I101,Valores!$K$1:$L$4,2,0),"Cumple","No cumple")),IF(S101<=VLOOKUP(K101,Valores!E:F,2,0),"Cumple","No cumple"))) -> No cumple | U101: =IFERROR(IF(T101="no cumple",S101-VLOOKUP(I101,Valores!$K$1:$L$4,2,0),0),S101-VLOOKUP(K101,Valores!E:F,2,0)) -> 7 | V101: Producción | W101: 35290 | Y101: Demora en proceso de pintura
A102: 46066 | B102: febrero | C102: 100297 | D102: Venta | E102: SQDM SAS / NELSON MOLINA | F102: TECU3FNPRO | G102: =IFERROR(VLOOKUP(F102,Productos!$A$2:$D$277,2,0)," ") -> Electric Standing Desk PRO Negro | H102: 1 | I102: =IFERROR(VLOOKUP(F102,Productos!$A$2:$D$277,3,0)," ") -> Standing Desk | J102: Bogotá y alrededores | K102: Bogotá | L102: =IF(O102>0,"Despachado","En alistamiento") -> Despachado | M102: Coordinadora | N102: 4122315-84151527663 | O102: 46077 | P102: 46078 | Q102: =IF(P102>0,"Entregado","En transito") -> Entregado | R102: =IF(L102="Despachado",NETWORKDAYS.INTL(A102,O102,11,Valores!$A$2:$A$19)-1,"PTE") -> 9 | S102: =IF(Q102="Entregado",NETWORKDAYS.INTL(A102,P102,11,Valores!$A$2:$A$19)-1,"PTE") -> 10 | T102: =IF(Q102="Entregado",IFERROR(IF(I102=VLOOKUP(I102,Valores!$K$1:$K$4,1,0),IF(S102<=VLOOKUP(I102,Valores!$K$1:$L$4,2,0),"Cumple","No cumple")),IF(S102<=VLOOKUP(K102,Valores!E:F,2,0),"Cumple","No cumple"))) -> No cumple | U102: =IFERROR(IF(T102="no cumple",S102-VLOOKUP(I102,Valores!$K$1:$L$4,2,0),0),S102-VLOOKUP(K102,Valores!E:F,2,0)) -> 7 | V102: Producción | W102: 44550 | Y102: Demora en proceso de pintura
...

Sheet Productos
A1: PRODUCTOS
A2: CODIGO | B2: PRODUCTO | C2: Categoria | D2: Valores Fletes
A3: TECUTRM8M | B3: Superficie Roble Miel 180x75 Moderno | C3: Superficie | D3: 35000
A4: TECUTRM8C | B4: Superficie Roble Miel 180x75 Clasico | C4: Superficie | D4: 35000
A5: TECUTRM5C | B5: Superficie Roble Miel 150x75 Clasico | C5: Superficie | D5: 35000
A6: TECUTRC8C | B6: Superficie Roble Caramelo 180x70 Clasico | C6: Superficie | D6: 35000
A7: TECUTRC5C | B7: Superficie Roble Caramelo 150x70 Clasico | C7: Superficie | D7: 35000
A8: TECUTNE | B8: Superficie orden especial Color: Wengue | C8: Superficie | D8: 35000
A9: TECUTBE | B9: Superficie orden especial Color: Niebla | C9: Superficie | D9: 35000
A10: TECUTCCE | B10: Superficie orden especial Color: Miel | C10: Superficie | D10: 35000
A11: TECUTCOE | B11: Superficie orden especial Color: Caramelo | C11: Superficie | D11: 35000
A12: TECUTB20C | B12: Superficie Niebla 200x70 Clasico | C12: Superficie | D12: 35000
A13: TECUTB9C | B13: Superficie Niebla 190x70 Clasico | C13: Superficie | D13: 35000
A14: TECUTB8M | B14: Superficie Niebla 180x70 Moderno | C14: Superficie | D14: 35000
... A176: TECURCC | B176: Repisa Miel | C176: Repisa | D176: 25000
A177: TECURFB-80 | B177: Repisa Flotante Niebla x 80cm | C177: Repisa
A178: TECURFB-70 | B178: Repisa Flotante Niebla x 70cm | C178: Repisa
A179: TECURFB-60 | B179: Repisa Flotante Niebla x 60cm | C179: Repisa
A180: TECURFN-80 | B180: Repisa Flotante Negro x 80cm | C180: Repisa
A181: TECURFN-70 | B181: Repisa Flotante Negro x 70cm | C181: Repisa
A182: TECURFN-60 | B182: Repisa Flotante Negro x 60cm | C182: Repisa
A183: TECURFFE -80 | B183: Repisa Flotante Fresno Europeo x 80cm | C183: Repisa
A184: TECURFFE -70 | B184: Repisa Flotante Fresno Europeo x 70cm | C184: Repisa
A185: TECURFFE -60 | B185: Repisa Flotante Fresno Europeo x 60cm | C185: Repisa
A186: TECURFCO-80 | B186: Repisa Flotante Caramelo x 80cm | C186: Repisa
A187: TECURFCO-70 | B187: Repisa Flotante Caramelo x 70cm | C187: Repisa
A188: TECURFCO-60 | B188: Repisa Flotante Caramelo x 60cm | C188: Repisa
... A200: TECURECO-110 | B200: Repisa Escritorio Caramelo x 110cm | C200: Repisa
A201: TECURCO | B201: Repisa Caramelo | C201: Repisa | D201: 25000
A202: TECUBLS | B202: Laptop Stand B | C202: Accesorio | D202: 50000
A203: TECUFX-T76 | B203: Escritorio FIjo Linea - T x 76,5 cm | C203: Escritorio Fijo
A204: TECUFX-T72 | B204: Escritorio FIjo Linea - T x 72,5 cm | C204: Escritorio Fijo
A205: TECUFX-T68 | B205: Escritorio FIjo Linea - T x 68,5 cm | C205: Escritorio Fijo
A206: TECUFX-T64 | B206: Escritorio FIjo Linea - T x 64,5 cm | C206: Escritorio Fijo
A207: TECU2FNG | B207: Electric Standing Desk GO Negro | C207: Standing Desk | D207: 40000
A208: TECU2FGGO | B208: Electric Standing Desk GO Gris | C208: Standing Desk | D208: 40000
A209: TECU2FBGO | B209: Electric Standing Desk GO Blanco | C209: Standing Desk | D209: 40000
A210: TECULFG | B210: Electric Standing Desk En L Frame Gris | C210: Standing Desk | D210: 40000
A211: TECU3FNCRO | B211: Electric Standing Desk PRO Negro circular | C211: Standing Desk | D211: 40000
A212: TECU3FNPRO | B212: Electric Standing Desk PRO Negro | C212: Standing Desk | D212: 40000
A213: TECU3FGPRO | B213: Electric Standing Desk PRO Gris | C213: Standing Desk | D213: 40000
A214: TECU3FBCRO | B214: Electric Standing Desk PRO Blanco circular | C214: Standing Desk | D214: 40000
A215: TECU3FBRO | B215: Electric Standing Desk PRO Blanco | C215: Standing Desk | D215: 40000
A216: TECULFN2 | B216: Electric Standing Desk En L Frame Negro 2.0 | C216: Standing Desk | D216: 40000
A217: TECUDSN | B217: Desk Stool Negra Silla ajustable | C217: Silla | D217: 25000
A218: TECUDSG | B218: Desk Stool Gris Silla ajustable | C218: Silla | D218: 25000
... A221: TECUBDPA | B221: Desk Pad B Negro Azul | C221: Accesorio | D221: 50000
A222: TECU2CURN-77 | B222: Cajonero 2.0 Unicolor Roble Negro x77cm | C222: Archivador
A223: TECU2CURN-73 | B223: Cajonero 2.0 Unicolor Roble Negro x73cm | C223: Archivador
A224: TECU2CURN-69 | B224: Cajonero 2.0 Unicolor Roble Negro x69cm | C224: Archivador
A225: TECU2CURN-65 | B225: Cajonero 2.0 Unicolor Roble Negro x65cm | C225: Archivador
A226: TECU2CUN-77 | B226: Cajonero 2.0 Unicolor Niebla x77cm | C226: Archivador
A227: TECU2CUN-73 | B227: Cajonero 2.0 Unicolor Niebla x73cm | C227: Archivador
A228: TECU2CUN-69 | B228: Cajonero 2.0 Unicolor Niebla x69cm | C228: Archivador
A229: TECU2CUN-65 | B229: Cajonero 2.0 Unicolor Niebla x65cm | C229: Archivador
A230: TECU2CUF-77 | B230: Cajonero 2.0 Unicolor Fresno Europeo x77cm | C230: Archivador
A231: TECU2CUF-73 | B231: Cajonero 2.0 Unicolor Fresno Europeo x73cm | C231: Archivador
A232: TECU2CUF-69 | B232: Cajonero 2.0 Unicolor Fresno Europeo x69cm | C232: Archivador
A233: TECU2CUF-65 | B233: Cajonero 2.0 Unicolor Fresno Europeo x65cm | C233: Archivador
... A253: TECU2CBC-65 | B253: Cajonero 2.0 Bicolor Caramelo x65cm | C253: Archivador
A254: TECUTBANPI | B254: Bandeja Piano | C254: Accesorio | D254: 35000
A255: TECUTBANTE | B255: Bandeja de teclado | C255: Accesorio | D255: 35000
A256: TECUCT | B256: Bandeja de cables | C256: Accesorio | D256: 25000
A257: TECUAFE | B257: Archivador TECU Fresno Europeo | C257: Archivador | D257: 50000
A258: TECUAN | B258: Archivador TECU Negro | C258: Archivador | D258: 50000
A259: TECUACC | B259: Archivador TECU Miel | C259: Archivador | D259: 50000
A260: TECUACO | B260: Archivador TECU Caramelo | C260: Archivador | D260: 50000
A261: TECUAB | B261: Archivador TECU Blanco (Niebla) | C261: Archivador | D261: 50000
A262: TECUTLN5x60 | B262: Superficie Escritorio en L Negro 150x60 | C262: Superficie
A263: TECUTLCO5x60 | B263: Superficie Escritorio Caramelo en L 150x60 | C263: Superficie
A264: TECUTLB5x60 | B264: Superficie Escritorio Niebla en L 150x60 | C264: Superficie
A265: TECUTLFE5X60 | B265: Superficie Escritorio Fresno Europeo en L 150x60 | C265: Superficie
A266: TECUTLN8x60 | B266: Superficie Escritorio en L Negro 180x60 | C266: Superficie
A267: TECUTLCO8x60 | B267: Superficie Escritorio Caramelo en L 180x60 | C267: Superficie
A268: TECUTLB8x60 | B268: Superficie Escritorio Niebla en L 180x60 | C268: Superficie
A269: TECUTLFE8X60 | B269: Superficie Escritorio Fresno Europeo en L 180x60 | C269: Superficie
A270: TECUTLN5x70 | B270: Superficie Escritorio en L Negro 150x70 | C270: Superficie
A271: TECUTLCO5x70 | B271: Superficie Escritorio Caramelo en L 150x70 | C271: Superficie
A272: TECUTLB5x70 | B272: Superficie Escritorio Niebla en L 150x70 | C272: Superficie
A273: TECUTLFE5X70 | B273: Superficie Escritorio Fresno Europeo en L 150x70 | C273: Superficie
... A277: TECUFX-E76 | B277: Escritorio FIjo Linea - E x 76,5 cm | C277: Escritorio Fijo

Sheet Indicadores Despachos
A1: INDICADORES OPERACIÓN LOGISTICA TECU
A5: 1- TIEMPOS DE DESPACHO Y ENTREGA
A7: Mes | B7: mayo | L7: Mes | M7: mayo
A8: Status Despacho | B8: Despachado | L8: Status entrega | M8: Entregado
A10: Promedio de Tiempo de despacho de orden | B10: Categoria | L10: Promedio de Tiempo de entrega de la orden | M10: Categoria
A11: Ciudad | B11: Standing Desk | C11: Superficie | D11: Accesorio | E11: Archivador | F11: Repisa | G11: Silla | H11: Ruedas | L11: Ciudad | M11: Standing Desk | N11: Superficie | O11: Accesorio | P11: Archivador | Q11: Repisa | R11: Silla | S11: Ruedas
A12: Bogotá y alrededores | B12: 0.625 | C12: 0.6 | D12: 1 | E12: 2.6666667 | F12: 0 | G12: 0 | H12: 0 | L12: Bogotá y alrededores | M12: 2 | N12: 2.5333333 | O12: 2.4285714 | P12: 4 | Q12: 2 | R12: 1 | S12: 1
A13: Antioquia | B13: 0.5 | C13: 0.66666667 | D13: 1 | H13: 0 | L13: Antioquia | M13: 1.5 | N13: 1.6666667 | O13: 2 | S13: 1
A14: Valle del Cauca | B14: 0 | C14: 0 | L14: Valle del Cauca | M14: 1 | N14: 1
A15: Atlantico | D15: 0 | G15: 0 | L15: Atlantico | O15: 2 | R15: 2
A16: Santander | B16: 0 | C16: 0 | L16: Santander | M16: 2 | N16: 2
A17: Caldas | B17: 1 | C17: 1 | L17: Caldas | M17: 10 | N17: 11
A28: 2. TIEMPOS DE DESPACHO Y DE ENTREGAS POR CIUDAD
A31: Mes | B31: mayo
A32: Status entrega | B32: Entregado
A34: Promedio de Tiempo de entrega de la orden | B34: Categoria
A35: Ciudad | B35: Standing Desk | C35: Superficie | D35: Accesorio | E35: Archivador | F35: Repisa | G35: Silla | H35: Ruedas | I35: Instalacion
A36: Bogotá y alrededores | B36: 2 | C36: 2.5333333 | D36: 2.4285714 | E36: 4 | F36: 2 | G36: 1 | H36: 1 | I36: #VALUE!
A37: Antioquia | B37: 1.5 | C37: 1.6666667 | D37: 2 | H37: 1 | I37: #VALUE!
A38: Valle del Cauca | B38: 1 | C38: 1
A39: Atlantico | D39: 2 | G39: 2
A40: Santander | B40: 2 | C40: 2
A41: Caldas | B41: 10 | C41: 11

Sheet OKR
A1: Indicador OTIF | E1: =D2*E31 -> 961.97778
A2: 1 a 3 días Ciudades principales 1 a 5 días Ciudades Secundarias | D2: =B13/(B13+C13) -> 0.81111111 | E2: NNS
J3: Enero | K3: 36
A4: Concepto | B4: Venta | J4: Garantias | K4: 6
A5: Status entrega | B5: Entregado | J5: A tiempo | K5: 20
J6: Fill rate | K6: =(K3-K4)/K3 -> 0.83333333
A7: Cuenta de No orden | B7: Cumple NNS
A8: Mes | B8: Cumple | C8: No cumple | D8: (en blanco) | E8: #N/D | F8: #¡VALOR! | G8: Total general | J8: OTIF | K8: =(K3-K4-K5)/K3 -> 0.27777778
A9: enero | B9: 70 | C9: 25 | G9: 95
A10: febrero | B10: 86 | C10: 5 | G10: 91
A11: marzo | B11: 60 | C11: 5 | G11: 65
A12: abril | B12: 111 | C12: 24 | E12: 3 | G12: 138
A13: mayo | B13: 73 | C13: 17 | E13: 12 | G13: 102
A14: junio | B14: 80 | C14: 8 | E14: 5 | G14: 93
A15: julio | B15: 80 | C15: 16 | E15: 9 | G15: 105
A16: agosto | B16: 44 | C16: 19 | E16: 6 | G16: 69
A17: septiembre | B17: 50 | C17: 12 | E17: 3 | F17: 2 | G17: 67
A18: octubre | B18: 76 | C18: 12 | E18: 12 | F18: 1 | G18: 101
A19: noviembre | B19: 115 | C19: 31 | E19: 12 | G19: 158
A20: diciembre | B20: 49 | C20: 30 | D20: 1 | E20: 3 | G20: 83
A21: Total general | B21: 894 | C21: 204 | D21: 1 | E21: 65 | F21: 3 | G21: 1167
A31: Garantias | E31: =B37/$B$38 -> 1186
A32: Mes | B32: (Todas)
A34: Cuenta de No orden
A35: Concepto | B35: Total
A36: Garantia | B36: 13
A37: Venta | B37: 1186
A38: RIFA | B38: 1
A39: Préstamo | B39: 4
A40: Cortesia | B40: 4
A41: Cambio | B41: 1
A42: Politica Satisfaccion | B42: 1
A43: Total general | B43: 1210
C47: Stock minimo
A48: Descripcion del producto | B48: Promedio mes | C48: n+4 | D48: Inventario actual | E48: COSTO | F48: FI | G48: TRM | H48: Costo
A49: Electric Standing Desk GO Negro | B49: 17 | C49: =B49*4 -> 68 | D49: 79 | E49: 122 | F49: 1.46 | G49: 4444.36 | H49: =((E49*F49)*G49)*D49 -> 62538723
A50: Electric Standing Desk GO Gris | B50: 2 | C50: =B50*4 -> 8 | D50: 0 | E50: 122 | F50: 1.46 | G50: 4444.36 | H50: =((E50*F50)*G50)*D50 -> 0
A51: Electric Standing Desk GO Blanco | B51: 4 | C51: =B51*4 -> 16 | D51: 21 | E51: 122 | F51: 1.46 | G51: 4444.36 | H51: =((E51*F51)*G51)*D51 -> 16624217
A52: Electric Standing Desk PRO Negro | B52: 15 | C52: 60 | D52: 58 | E52: 125 | F52: 1.46 | G52: 4444.36 | H52: =((E52*F52)*G52)*D52 -> 47043551
A53: Electric Standing Desk PRO Negro circular | B53: 15 | C53: 60 | D53: 15 | E53: 125 | F53: 1.46 | G53: 4444.36 | H53: =((E53*F53)*G53)*D53 -> 12166436
A54: Electric Standing Desk PRO Gris | B54: 3.3333333 | C54: 13 | D54: 0 | E54: 125 | F54: 1.46 | G54: 4444.36 | H54: =((E54*F54)*G54)*D54 -> 0
A55: Electric Standing Desk PROBlanco | B55: 4 | C55: =B55*4 -> 16 | D55: 17 | E55: 125 | F55: 1.46 | G55: 4444.36 | H55: =((E55*F55)*G55)*D55 -> 13788627
A56: Electric Standing Desk PROBlanco circular | B56: 4 | C56: =B56*4 -> 16 | D56: 5 | E56: 125 | F56: 1.46 | G56: 4444.36 | H56: =((E56*F56)*G56)*D56 -> 4055478.5
A57: Electric Standing Desk | Escritorio Ajustable En L Frame Negro | B57: 3 | C57: =B57*4 -> 12 | D57: 31 | E57: 125 | F57: 1.46 | G57: 4444.36 | H57: =((E57*F57)*G57)*D57 -> 25143967
B58: =SUM(B49:B57) -> 67.333333 | C58: =B58*4 -> 269.33333 | D58: =SUM(D49:D57) -> 226 | H58: =SUM(H49:H57) -> 1.81361e+08
H59: =D76 -> 4508229
H60: =SUM(H58:H59) -> 1.8586923e+08
A62: Superficie | B62: Inventario actual | C62: Costo | D62: Costo total
A63: Caramelo clasicas | B63: 3 | C63: 195840 | D63: =C63*B63 -> 587520
A64: Miel clasicas | B64: 1 | C64: 195840 | D64: =C64*B64 -> 195840
A65: Niebla Clasicas | B65: 5 | C65: 249154 | D65: =C65*B65 -> 1245770
A66: Negro Clasicas | B66: 2 | C66: 249154 | D66: =C66*B66 -> 498308
A67: Caramelo modernas | B67: 0 | C67: 167849 | D67: =C67*B67 -> 0
A68: Miel modernas | B68: 1 | C68: 167849 | D68: =C68*B68 -> 167849
A69: Niebla modernas | B69: 5 | C69: 220988 | D69: =C69*B69 -> 1104940
A70: Negro modernas | B70: 0 | C70: 220988 | D70: =C70*B70 -> 0
A71: Caramelo en L | B71: 1 | C71: 218349 | D71: =C71*B71 -> 218349
A72: Miel en L | B72: 1 | C72: 218349 | D72: =C72*B72 -> 218349
A73: Niebla en L | B73: 1 | C73: 271304 | D73: =C73*B73 -> 271304 | F73: **Martes programar reunion expansion de planeamiento
A74: Negro en L | B74: 0 | C74: 271304 | D74: =C74*B74 -> 0
A76: Total | B76: =SUM(B63:B74) -> 20 | D76: =SUM(D63:D74) -> 4508229
A82: Superficie | B82: Inventario actual | C82: Costo | D82: Costo total
A83: Desk Stool Negra | B83: 3 | C83: 195840 | D83: =C83*B83 -> 587520
A84: Desk Stool Gris | B84: 1 | C84: 195840 | D84: =C84*B84 -> 195840
A85: Niebla Clasicas | B85: 5 | C85: 249154 | D85: =C85*B85 -> 1245770
A86: Negro Clasicas | B86: 2 | C86: 249154 | D86: =C86*B86 -> 498308
A87: Caramelo modernas | B87: 0 | C87: 167849 | D87: =C87*B87 -> 0
A88: Miel modernas | B88: 1 | C88: 167849 | D88: =C88*B88 -> 167849
A89: Niebla modernas | B89: 5 | C89: 220988 | D89: =C89*B89 -> 1104940
A90: Negro modernas | B90: 0 | C90: 220988 | D90: =C90*B90 -> 0
A91: Caramelo en L | B91: 1 | C91: 218349 | D91: =C91*B91 -> 218349
A92: Miel en L | B92: 1 | C92: 218349 | D92: =C92*B92 -> 218349
A93: Niebla en L | B93: 1 | C93: 271304 | D93: =C93*B93 -> 271304
A94: Negro en L | B94: 0 | C94: 271304 | D94: =C94*B94 -> 0
A96: Total | B96: =SUM(B83:B94) -> 20 | D96: =SUM(D83:D94) -> 4508229

Sheet Analisis Ventas
B2: INDICADORES VENTAS TECU.CO
A4: 1. RESUMEN DE VENTAS
A5: Concepto | B5: Venta
A7: Suma de Cantidad | B7: Categoria
A8: Mes | B8: Standing Desk | C8: Superficie | D8: Accesorio | E8: Archivador | F8: Repisa | G8: Silla | H8: Instalación | I8: Fijo | J8: Total general
A9: enero | B9: 23 | C9: 21 | D9: 15 | E9: 7 | F9: 7 | G9: 1 | H9: 4 | J9: 78
A10: febrero | B10: 17 | C10: 16 | D10: 9 | E10: 3 | F10: 4 | H10: 1 | I10: 3 | J10: 53
A11: Total general | B11: 40 | C11: 37 | D11: 24 | E11: 10 | F11: 11 | G11: 1 | H11: 5 | I11: 3 | J11: 131
E12: **Variacion porcentual
B13: =(B10-B9)/B9 -> -0.26086957 | C13: =(C10-C9)/C9 -> -0.23809524 | D13: =(D10-D9)/D9 -> -0.4 | E13: =(E10-E9)/E9 -> -0.57142857 | F13: =(F10-F9)/F9 -> -0.42857143 | G13: =(G10-G9)/G9 -> -1 | H13: =(H10-H9)/H9 -> -0.75 | I13: =(I10-I9)/I9 -> #DIV/0! | J13: =(J10-J9)/J9 -> -0.32051282
A25: Mes | B25: (Todas)
A26: Concepto | B26: Venta
A28: Suma de Cantidad | B28: Categoria
A29: Ciudad | B29: Standing Desk | C29: Superficie | D29: Repisa | E29: Accesorio | F29: Archivador | G29: Silla | H29: Instalación | I29: Fijo | J29: Total general
A30: Bogotá y alrededores | B30: 21 | C30: 20 | D30: 6 | E30: 13 | F30: 4 | H30: 4 | I30: 3 | J30: 71
A31: Antioquia | B31: 9 | C31: 8 | E31: 4 | F31: 2 | H31: 1 | J31: 24
A32: Tolima | B32: 1 | C32: 1 | D32: 2 | E32: 5 | G32: 1 | J32: 10
A33: Quindío | B33: 3 | C33: 3 | F33: 3 | J33: 9
A34: Valle del Cauca | B34: 2 | C34: 2 | D34: 1 | E34: 1 | F34: 1 | J34: 7
A35: Cesar | B35: 1 | C35: 1 | D35: 1 | J35: 3
A36: Meta | B36: 1 | C36: 1 | J36: 2
A37: Cauca | B37: 1 | C37: 1 | J37: 2
A38: Bolívar | D38: 1 | J38: 1
A39: Cundinamarca | E39: 1 | J39: 1
A40: Caldas | B40: 1 | J40: 1
A41: Total general | B41: 40 | C41: 37 | D41: 11 | E41: 24 | F41: 10 | G41: 1 | H41: 5 | I41: 3 | J41: 131
A78: Mes | B78: (Todas)
A79: Concepto | B79: Venta
A81: Suma de Cantidad | B81: Categoria
A82: Lugar de entrega | B82: Standing Desk | C82: Superficie | D82: Repisa | E82: Accesorio | F82: Archivador | G82: Silla | H82: Instalación | I82: Fijo | J82: Total general
A83: Bogotá | B83: 21 | C83: 20 | D83: 6 | E83: 11 | F83: 4 | H83: 4 | I83: 3 | J83: 69
A84: Medellín | B84: 5 | C84: 5 | E84: 2 | H84: 1 | J84: 13
A85: Ibagué | B85: 1 | C85: 1 | D85: 2 | E85: 5 | G85: 1 | J85: 10
A86: Armenia | B86: 3 | C86: 3 | F86: 3 | J86: 9
A87: Jamundí | B87: 1 | C87: 1 | D87: 1 | E87: 1 | J87: 4
A88: Sabaneta | B88: 1 | C88: 1 | F88: 2 | J88: 4
A89: Valledupar | B89: 1 | C89: 1 | D89: 1 | J89: 3
A90: El Retiro | B90: 1 | C90: 1 | E90: 1 | J90: 3
A91: Chía | E91: 2 | J91: 2
A92: Itagui | B92: 1 | C92: 1 | J92: 2
A93: Villavicencio | B93: 1 | C93: 1 | J93: 2
A94: Cali | B94: 1 | C94: 1 | J94: 2
A95: Popayán | B95: 1 | C95: 1 | J95: 2
A96: Cartagena | D96: 1 | J96: 1
A97: Tuluá | F97: 1 | J97: 1
A98: La ceja | E98: 1 | J98: 1
A99: Copacabana | B99: 1 | J99: 1
A100: Manizales | B100: 1 | J100: 1
A101: Mosquera | E101: 1 | J101: 1
A102: Total general | B102: 40 | C102: 37 | D102: 11 | E102: 24 | F102: 10 | G102: 1 | H102: 5 | I102: 3 | J102: 131
A111: Mes | B111: (Todas)
A113: Suma de Valor despacho | B113: Categoria
A114: Ciudad | B114: Standing Desk | C114: Superficie | D114: Repisa | E114: Accesorio | F114: Archivador | G114: Silla | H114: Instalación | I114: Fijo | J114: Total general
A115: Bogotá y alrededores | B115: 959924 | C115: 580793 | D115: 101932 | E115: 311278 | F115: 239228 | H115: 0 | I115: 155176 | J115: 2348331
A116: Antioquia | B116: 399647 | C116: 291790 | E116: 70201 | F116: 136654 | H116: 0 | J116: 898292
A117: Valle del Cauca | B117: 86228 | C117: 61242 | D117: 0 | E117: 26681 | F117: 71906 | J117: 246057
A118: Tolima | B118: 65353 | C118: 40366 | D118: 0 | E118: 44468 | G118: 27803 | J118: 177990
A119: Cauca | B119: 47674 | C119: 63014 | J119: 110688
A120: Caldas | B120: 35044 | J120: 35044
A121: Cundinamarca | E121: 26681 | J121: 26681
A122: Quindío | B122: 50000 | C122: 40000 | F122: 100000 | J122: 190000
A123: Bolívar | D123: 40669 | J123: 40669
A124: Meta | B124: 65599 | C124: 63431 | J124: 129030
A125: Cesar | B125: 62759 | C125: 42089 | D125: 0 | J125: 104848
A126: Total general | B126: 1772228 | C126: 1182725 | D126: 142601 | E126: 479309 | F126: 547788 | G126: 27803 | H126: 0 | I126: 155176 | J126: 4307630
B138: Valores
A139: Mes | B139: Suma de Valor despacho | C139: Suma de Cantidad
A140: enero | B140: 4094684 | C140: 120
A141: Total general | B141: 4094684 | C141: 120
A161: Concepto | B161: (Todas)
A163: Suma de Cantidad | C163: Mes
A164: Categoria | B164: Descripcion del producto | C164: octubre | D164: noviembre | E164: Total general
A165: Archivador | B165: Cajonero 2.0 Bicolor Caramelo x65cm | D165: 2 | E165: 2
B166: Cajonero 2.0 Bicolor Caramelo x73cm | C166: 1 | D166: 1 | E166: 2
B167: Cajonero 2.0 Bicolor Caramelo x77cm | C167: 1 | E167: 1
B168: Cajonero 2.0 Bicolor Fresno Europeo x73cm | D168: 1 | E168: 1
A169: Total Archivador | C169: 2 | D169: 4 | E169: 6
A170: Total general | C170: 2 | D170: 4 | E170: 6
A341: Suma de Valor despacho
A342: Mes | B342: Total
A343: enero | B343: 4094684
A344: febrero | B344: 2281360
A345: marzo | B345: 3070108
A346: abril | B346: 2942555
A347: mayo | B347: 2329766
A348: Total general | B348: 14718473
A361: Mes | B361: mayo
A363: Suma de Valor despacho | B363: Categoria
A364: Ciudad | B364: Standing Desk | C364: Superficie | D364: Repisa | E364: Accesorio | F364: Archivador | G364: Silla | H364: Ruedas | I364: Instalacion | J364: Total general
A365: Bogotá y alrededores | B365: 741579 | C365: 383971 | D365: 23429 | E365: 157659 | F365: 175540 | G365: 53218 | H365: 23875 | I365: 0 | J365: 1559271
A366: Antioquia | B366: 176684 | C366: 81427 | E366: 27929 | H366: 23875 | I366: 0 | J366: 309915
A367: Valle del Cauca | B367: 128763 | C367: 76927 | J367: 205690
A368: Atlantico | E368: 24885 | G368: 81884 | J368: 106769
A369: Santander | B369: 56077 | C369: 41897 | J369: 97974
A370: Caldas | B370: 34953 | C370: 15194 | J370: 50147
A371: Total general | B371: 1138056 | C371: 599416 | D371: 23429 | E371: 210473 | F371: 175540 | G371: 135102 | H371: 47750 | I371: 0 | J371: 2329766
A385: Suma de Valor despacho
A386: Mes | B386: Total
A387: enero | B387: 4094684
A388: febrero | B388: 2032202
...

Sheet Valores
A1: dias Festivos | D1: Ciudad entrega | E1: Lugar entrega | F1: Tiempo entrega | H1: Concepto | K1: Concepto | L1: Dias entrega | O1: Causales de incumplimiento
A2: 46023 | D2: Acacias | E2: Meta | F2: 5 | H2: Venta | K2: Bibliotecas | L2: 15 | O2: Demora en proceso de pintura
A3: 46034 | D3: Aguachica | E3: Aguachica | F3: 5 | H3: Garantia | K3: Fijo | L3: 10 | O3: Demora en proceso de producción
A4: 46104 | D4: Antioquia | E4: Envigado | F4: 3 | H4: Cortesia | K4: Archivador | L4: 5 | O4: Demora en proceso de producción- Novedad en el reparto
A5: 46114 | D5: Antioquia | E5: Medellín | F5: 3 | H5: Novedad | O5: Disponibilidad materia prima
A6: 46115 | D6: Antioquia | E6: Bello | F6: 3 | O6: Ausencia del cliente
A7: 46143 | D7: Antioquia | E7: Sabaneta | F7: 3 | O7: Demora en entrega
A8: 46160 | D8: Antioquia | E8: La estrella | F8: 3
A9: 46181 | D9: Antioquia | E9: El retiro | F9: 5
A10: 46188 | D10: Antioquia | E10: Caldas | F10: 5
A11: 46202 | D11: Antioquia | E11: La ceja | F11: 5
A12: 46223 | D12: Antioquia | E12: Itagui | F12: 3
A13: 46241 | D13: Antioquia | E13: Rionegro | F13: 3
A14: 46251 | D14: Antioquia | E14: Guarne | F14: 5
A15: 46307 | D15: Antioquia | E15: Carmen de Viboral | F15: 5
A16: 46328 | D16: Antioquia | E16: Retiro | F16: 5
A17: 46342 | D17: Antioquia | E17: San Vicente | F17: 5
A18: 46364 | D18: Antioquia | E18: Marinilla | F18: 5
A19: 46381 | D19: Antioquia | E19: Copacabana | F19: 5
D20: Quindio | E20: Armenia | F20: 3
D21: Atlantico | E21: Soledad | F21: 5
D22: Atlantico | E22: Barranquilla | F22: 5
D23: Bogotá y alrededores | E23: Bogotá | F23: 3
D24: Bogotá y alrededores | E24: Cajica | F24: 5
D25: Bogotá y alrededores | E25: Bojaca | F25: 5
D26: Bogotá y alrededores | E26: Zipaquira | F26: 5
D27: Bogotá y alrededores | E27: Choachi | F27: 5
D28: Bogotá y alrededores | E28: Chía | F28: 5
D29: Bogotá y alrededores | E29: Fusagasuga | F29: 5
D30: Bogotá y alrededores | E30: Mosquera | F30: 5
D31: Bogotá y alrededores | E31: Tocancipa | F31: 5
... D67: Santander | E67: Barrancabermeja | F67: 5

Sheet Graficos Finales
A1: Mes | B1: Standing Desk | C1: Superficie | D1: Accesorio | E1: Archivador | F1: Repisa | G1: Silla | H1: Ruedas | I1: Instalaciones | J1: Total general
A2: Diciembre | B2: 30 | C2: 31 | D2: 10 | E2: 9 | F2: 6 | G2: 2 | I2: 7 | J2: =SUM(B2:I2) -> 95
A3: Enero | B3: 40 | C3: 35 | D3: 18 | E3: 2 | F3: 3 | G3: 3 | H3: 4 | I3: 10 | J3: 115 | K3: =(B3-B2)/B2 -> 0.33333333
A4: Febrero | B4: 22 | C4: 20 | D4: 10 | E4: 7 | F4: 1 | H4: 4 | I4: 2 | J4: 66 | K4: =(B4-B3)/B3 -> -0.45
A5: Marzo | B5: 35 | C5: 36 | D5: 7 | E5: 3 | F5: 4 | H5: 3 | I5: 7 | J5: 95 | K5: =(B5-B4)/B4 -> 0.59090909
A6: Abril | B6: 35 | C6: 33 | D6: 16 | E6: 3 | F6: 3 | G6: 5 | H6: 3 | I6: 7 | J6: 105 | K6: =(B6-B5)/B5 -> 0
A7: Mayo | B7: 25 | C7: 24 | D7: 12 | E7: 4 | F7: 1 | G7: 4 | H7: 4 | I7: 6 | J7: 80 | K7: =(B7-B6)/B6 -> -0.28571429
A8: Total general | B8: =SUM(B2:B5) -> 127 | C8: =SUM(C2:C5) -> 122 | D8: =SUM(D2:D5) -> 45 | E8: =SUM(E2:E5) -> 21 | F8: =SUM(F2:F5) -> 14 | G8: =SUM(G2:G5) -> 5 | H8: =SUM(H2:H5) -> 11 | I8: =SUM(I2:I5) -> 26 | J8: =SUM(J2:J5) -> 371
A13: Ventas por Lugar de entrega
A15: Ciudad | B15: Standing Desk | C15: Superficie | D15: Repisa | E15: Accesorio | F15: Archivador | G15: Silla | H15: Ruedas | I15: Instalacion | J15: Total general
A16: Bogotá y alrededores | B16: 16 | C16: 16 | D16: 1 | E16: 10 | F16: 4 | G16: 2 | H16: 2 | I16: 4 | J16: 55
A17: Antioquia | B17: 4 | C17: 3 | E17: 1 | H17: 2 | I17: 2 | J17: 12 | M17: Ciudad | N17: Standing Desk
A18: Valle del Cauca | B18: 3 | C18: 3 | J18: 6 | M18: Bogotá y alrededores | N18: 55
A19: Atlantico | E19: 1 | G19: 2 | J19: 3 | M19: Antioquia | N19: 12
A20: Caldas | B20: 1 | C20: 1 | J20: 2 | M20: Valle del Cauca | N20: 6
A21: Santander | B21: 1 | C21: 1 | J21: 2 | M21: Atlantico | N21: 3
A22: Total general | B22: 25 | C22: 24 | D22: 1 | E22: 12 | F22: 4 | G22: 4 | H22: 4 | I22: 6 | J22: 80 | M22: Caldas | N22: 2
M23: Santander | N23: 2
M24: Total general | N24: 80
A34: Ventas por Ciudad
A36: Suma de Cantidad | B36: Categoria | M36: Lugar de entrega | N36: Qty Ventas
A37: Lugar de entrega | B37: Standing Desk | C37: Superficie | D37: Repisa | E37: Accesorio | F37: Archivador | G37: Silla | H37: Ruedas | I37: Instalacion | J37: Total general | M37: Bogota | N37: 45
A38: Bogota | B38: 13 | C38: 13 | E38: 8 | F38: 3 | G38: 2 | H38: 2 | I38: 4 | J38: 45 | M38: Medellin | N38: 6
A39: Medellin | B39: 2 | C39: 1 | E39: 1 | I39: 2 | J39: 6 | M39: Chia | N39: 4
A40: Chia | B40: 1 | C40: 1 | E40: 1 | F40: 1 | J40: 4 | M40: Cali | N40: 4
A41: Cali | B41: 2 | C41: 2 | J41: 4 | M41: Barranquilla | N41: 3
A42: Barranquilla | E42: 1 | G42: 2 | J42: 3 | M42: Funza | N42: 2
A43: Funza | B43: 1 | C43: 1 | J43: 2 | M43: Retiro | N43: 2
A44: Retiro | B44: 1 | C44: 1 | J44: 2 | M44: Soacha | N44: 2
A45: Soacha | B45: 1 | C45: 1 | J45: 2 | M45: Envigado | N45: 2
A46: Envigado | H46: 2 | J46: 2 | M46: Palmira | N46: 2
A47: Palmira | B47: 1 | C47: 1 | J47: 2 | M47: Cajica | N47: 2
A48: Cajica | D48: 1 | E48: 1 | J48: 2 | M48: Bucaramanga | N48: 2
A49: Bucaramanga | B49: 1 | C49: 1 | J49: 2 | M49: Manizales | N49: 2
A50: Manizales | B50: 1 | C50: 1 | J50: 2 | M50: Carmen de Viboral | N50: 2
A51: Carmen de Viboral | B51: 1 | C51: 1 | J51: 2 | M51: Total general | N51: 80
A52: Total general | B52: 25 | C52: 24 | D52: 1 | E52: 12 | F52: 4 | G52: 4 | H52: 4 | I52: 6 | J52: 80
A65: TIEMPO DESPACHO
J67: Ciudad | K67: Standing Desk | L67: Superficie
A68: Ciudad | B68: Standing Desk | C68: Superficie | D68: Accesorio | E68: Archivador | F68: Repisa | G68: Silla | H68: Ruedas | J68: Bogotá y alrededores | K68: 0.625 | L68: 0.6
A69: Bogotá y alrededores | B69: 0.625 | C69: 0.6 | D69: 1 | E69: 2.6666667 | F69: 0 | G69: 0 | H69: 0 | J69: Antioquia | K69: 0.5 | L69: 0.66666667
A70: Antioquia | B70: 0.5 | C70: 0.66666667 | D70: 1 | H70: 0 | J70: Valle del Cauca | K70: 0 | L70: 0
A71: Valle del Cauca | B71: 0 | C71: 0 | J71: Santander | K71: 0 | L71: 0
A72: Atlantico | D72: 0 | G72: 0 | J72: Caldas | K72: 1 | L72: 1
A73: Santander | B73: 0 | C73: 0
A74: Caldas | B74: 1 | C74: 1
A97: TIEMPO DE ENTREGA
A99: Ciudad | B99: Standing Desk | C99: Superficie | D99: Accesorio | E99: Archivador | F99: Repisa | G99: Silla | H99: Ruedas | J99: Ciudad | K99: Standing Desk | L99: Superficie
A100: Bogotá y alrededores | B100: 2 | C100: 2.5333333 | D100: 2.4285714 | E100: 4 | F100: 2 | G100: 1 | H100: 1 | J100: Bogotá y alrededores | K100: 2 | L100: 2.5333333
A101: Antioquia | B101: 1.5 | C101: 1.6666667 | D101: 2 | H101: 1 | J101: Antioquia | K101: 1.5 | L101: 1.6666667
A102: Valle del Cauca | B102: 1 | C102: 1 | J102: Valle del Cauca | K102: 1 | L102: 1
A103: Atlantico | D103: 2 | G103: 2 | J103: Santander | K103: 2 | L103: 2
A104: Santander | B104: 2 | C104: 2 | J104: Caldas | K104: 10 | L104: 11
A105: Caldas | B105: 10 | C105: 11
C140: Stock minimo
A141: Descripcion del producto | B141: Promedio mes | C141: n+4 | D141: Inventario actual | E141: COSTO | F141: FI | G141: TRM | H141: Costo
A142: Electric Standing Desk GO Negro | B142: 17 | C142: 68 | D142: 75 | E142: 115 | F142: 1.46 | G142: 4444 | H142: 84435114
A143: Electric Standing Desk GO Gris | B143: 2 | C143: 8 | E143: 115 | F143: 1.46 | G143: 4444 | H143: 15691481
A144: Electric Standing Desk GO Blanco | B144: 4 | C144: 16 | D144: 19 | E144: 122 | F144: 1.46 | G144: 4444 | H144: 14944268
A145: Electric Standing Desk PRO Negro | B145: 15 | C145: 60 | D145: 58 | E145: 122 | F145: 1.46 | G145: 4444 | H145: 45169662
A146: Electric Standing Desk PRO Negro circular | B146: 15 | C146: 60 | D146: 9 | E146: 127 | F146: 1.46 | G146: 4444 | H146: 45169662
A147: Electric Standing Desk PRO Gris | B147: 3 | C147: 13 | D147: 0 | E147: 122 | F147: 1.46 | G147: 4444 | H147: 19905275
A148: Electric Standing Desk PROBlanco | B148: 4 | C148: 16 | D148: 14 | E148: 122 | F148: 1.46 | G148: 4444 | H148: 14546162
A149: Electric Standing Desk PROBlanco circular | B149: 4 | C149: 16 | D149: 4 | E149: 127 | F149: 1.46 | G149: 4444 | H149: 14546162
A150: Electric Standing Desk | Escritorio Ajustable En L Frame Negro | B150: 3 | C150: 12 | D150: 28 | E150: 190 | F150: 1.46 | G150: 4444 | H150: 9952637.5
B151: 48 | C151: 193 | D151: =SUM(D142:D150) -> 207 | H151: 2.046446e+08

Sheet Graficos causales
A3: Cuenta de No orden | B3: Etiquetas de columna
A4: Etiquetas de fila | B4: enero | C4: Total general
A5: Cumple | B5: 49 | C5: 49
A6: No cumple | B6: 23 | C6: 23
A7: Total general | B7: 72 | C7: 72
A17: Cumple NNS | B17: No cumple
A19: Cuenta de No orden | B19: Etiquetas de columna
A20: Etiquetas de fila | B20: enero | C20: Total general
A21: Demora en proceso de producción | B21: 6 | C21: 6 | D21: =B21/$B$27 -> 0.26086957
A22: Disponibilidad materia prima | B22: 6 | C22: 6 | D22: =B22/$B$27 -> 0.26086957
A23: Demora en proceso de pintura | B23: 5 | C23: 5 | D23: =B23/$B$27 -> 0.2173913
A24: Demora en entrega | B24: 3 | C24: 3 | D24: =B24/$B$27 -> 0.13043478
A25: Ausencia del cliente | B25: 2 | C25: 2 | D25: =B25/$B$27 -> 0.086956522
A26: Demora en proceso de producción- Novedad en el reparto | B26: 1 | C26: 1 | D26: =B26/$B$27 -> 0.043478261
A27: Total general | B27: 23 | C27: 23 | D27: =B27/$B$27 -> 1
A33: Cumple NNS | B33: No cumple
A35: Cuenta de No orden | B35: Etiquetas de columna
A36: Etiquetas de fila | B36: enero | C36: Total general
A37: Cliente | B37: 2 | C37: 2
A38: Producción | B38: 16 | C38: 16
A39: Producción - Transporte | B39: 4 | C39: 4
A40: Transporte | B40: 1 | C40: 1
A41: Total general | B41: 23 | C41: 23
